[
  {
    "customer": [
      {
        "id": "36103c62-a609-45de-86de-76abb46414d4",
        "first_name": "John",
        "last_name": "Doe",
        "email": "john.doe@example.com",
        "address": "123 Main St",
        "city": "New York",
        "state": "NY",
        "zip_code": "10001",
        "created_at": "2023-09-13T22:09:09.407Z",
        "updated_at": "2023-09-13T18:47:45.048Z",
        "user_id": "user_entity_pk"
      },
      {
        "id": "692f7495-9e71-49bc-aa8e-072d08b5a85e",
        "first_name": "Jane",
        "last_name": "Smith",
        "email": "jane.smith@example.com",
        "address": "456 Elm St",
        "city": "Los Angeles",
        "state": "CA",
        "zip_code": "90001",
        "created_at": "2023-09-13T09:05:09.555Z",
        "updated_at": "2023-09-14T04:15:01.038Z",
        "user_id": "user_entity_pk"
      },
      {
        "id": "ea5681a8-30e6-4b99-9e35-3f8156eadb84",
        "first_name": "Michael",
        "last_name": "Brown",
        "email": "michael.brown@example.com",
        "address": "789 Oak St",
        "city": "Chicago",
        "state": "IL",
        "zip_code": "60601",
        "created_at": "2023-09-13T19:24:59.724Z",
        "updated_at": "2023-09-13T14:42:56.752Z",
        "user_id": "user_entity_pk"
      },
      {
        "id": "3fd60405-60f7-4651-b3bb-5346257534cd",
        "first_name": "Sarah",
        "last_name": "Johnson",
        "email": "sarah.johnson@example.com",
        "address": "321 Pine St",
        "city": "Houston",
        "state": "TX",
        "zip_code": "77001",
        "created_at": "2023-09-14T03:23:14.262Z",
        "updated_at": "2023-09-13T13:22:13.083Z",
        "user_id": "user_entity_pk"
      },
      {
        "id": "12f03fed-da4f-4aec-94b3-0c77d0744874",
        "first_name": "Robert",
        "last_name": "Wilson",
        "email": "robert.wilson@example.com",
        "address": "654 Maple St",
        "city": "Phoenix",
        "state": "AZ",
        "zip_code": "85001",
        "created_at": "2023-09-13T17:22:31.389Z",
        "updated_at": "2023-09-14T01:59:19.250Z",
        "user_id": "user_entity_pk"
      }
    ],
    "service": [
      {
        "id": "2f7a5a6d-8209-4ae8-b6a1-99821cb57ee9",
        "name": "Web Design",
        "description": "Custom website design and development",
        "price": 17398,
        "duration": 51816,
        "created_at": "2023-09-13T17:50:50.924Z",
        "updated_at": "2023-09-13T13:49:30.445Z",
        "company_id": "main_entity_pk"
      },
      {
        "id": "561b1583-f4de-4a24-a149-a87031aedd89",
        "name": "Mobile App Development",
        "description": "iOS and Android app development",
        "price": 36462,
        "duration": 29439,
        "created_at": "2023-09-13T13:00:52.840Z",
        "updated_at": "2023-09-13T06:24:35.360Z",
        "company_id": "main_entity_pk"
      },
      {
        "id": "b98e0345-d5ad-48d8-bcde-fc2098964296",
        "name": "SEO Services",
        "description": "Improve search engine rankings",
        "price": 53105,
        "duration": 92323,
        "created_at": "2023-09-14T00:22:37.379Z",
        "updated_at": "2023-09-13T20:12:34.555Z",
        "company_id": "main_entity_pk"
      },
      {
        "id": "f1c46c3e-b658-4ab3-a7c4-1258894a0e48",
        "name": "Social Media Marketing",
        "description": "Promote brand on social media platforms",
        "price": 18181,
        "duration": 14059,
        "created_at": "2023-09-13T22:39:01.004Z",
        "updated_at": "2023-09-13T17:04:34.460Z",
        "company_id": "main_entity_pk"
      },
      {
        "id": "a373d8bd-450e-45bb-94be-55faeaac1c21",
        "name": "Cloud Consulting",
        "description": "Migrate to cloud infrastructure",
        "price": 25873,
        "duration": 99571,
        "created_at": "2023-09-13T06:32:44.120Z",
        "updated_at": "2023-09-13T17:31:10.977Z",
        "company_id": "main_entity_pk"
      }
    ],
    "request": [
      {
        "id": "3b780720-f1b9-484e-9c09-8267d7c028a5",
        "status": "Pending",
        "created_at": "2023-09-14T00:47:45.084Z",
        "updated_at": "2023-09-13T17:03:11.832Z",
        "company_id": "main_entity_pk",
        "customer_id": "36103c62-a609-45de-86de-76abb46414d4",
        "service_id": "f1c46c3e-b658-4ab3-a7c4-1258894a0e48"
      },
      {
        "id": "b6ef89ac-7133-48f8-89fb-bb9abf9cc0bc",
        "status": "In Progress",
        "created_at": "2023-09-13T11:05:35.841Z",
        "updated_at": "2023-09-13T18:27:58.498Z",
        "company_id": "main_entity_pk",
        "customer_id": "692f7495-9e71-49bc-aa8e-072d08b5a85e",
        "service_id": "a373d8bd-450e-45bb-94be-55faeaac1c21"
      },
      {
        "id": "132094db-53f4-49ea-9f67-5fc7fe31fb80",
        "status": "Completed",
        "created_at": "2023-09-13T23:35:44.219Z",
        "updated_at": "2023-09-14T03:15:50.979Z",
        "company_id": "main_entity_pk",
        "customer_id": "3fd60405-60f7-4651-b3bb-5346257534cd",
        "service_id": "561b1583-f4de-4a24-a149-a87031aedd89"
      },
      {
        "id": "5b6fa877-6ed3-454d-a091-e467c95cce87",
        "status": "Cancelled",
        "created_at": "2023-09-13T16:20:29.086Z",
        "updated_at": "2023-09-14T02:14:50.703Z",
        "company_id": "main_entity_pk",
        "customer_id": "ea5681a8-30e6-4b99-9e35-3f8156eadb84",
        "service_id": "2f7a5a6d-8209-4ae8-b6a1-99821cb57ee9"
      },
      {
        "id": "b2d0c699-cc5f-49d6-9e9e-192e4387db27",
        "status": "On Hold",
        "created_at": "2023-09-13T15:33:27.718Z",
        "updated_at": "2023-09-13T17:58:50.232Z",
        "company_id": "main_entity_pk",
        "customer_id": "12f03fed-da4f-4aec-94b3-0c77d0744874",
        "service_id": "2f7a5a6d-8209-4ae8-b6a1-99821cb57ee9"
      }
    ],
    "representative": [
      {
        "id": "2e709a98-87cb-447a-b64e-72400dd843e6",
        "first_name": "John",
        "last_name": "Doe",
        "email": "john.doe@example.com",
        "created_at": "2023-09-13T11:01:27.538Z",
        "updated_at": "2023-09-13T10:34:54.477Z",
        "company_id": "main_entity_pk",
        "user_id": "user_entity_pk"
      },
      {
        "id": "ec9c1c58-70af-4582-8d84-d56b34745757",
        "first_name": "Jane",
        "last_name": "Smith",
        "email": "jane.smith@example.com",
        "created_at": "2023-09-13T18:50:16.407Z",
        "updated_at": "2023-09-13T15:56:46.183Z",
        "company_id": "main_entity_pk",
        "user_id": "user_entity_pk"
      },
      {
        "id": "c1986ab1-e79a-4585-94d3-8a522cb75a4f",
        "first_name": "Michael",
        "last_name": "Brown",
        "email": "michael.brown@example.com",
        "created_at": "2023-09-13T10:45:31.437Z",
        "updated_at": "2023-09-14T01:31:58.081Z",
        "company_id": "main_entity_pk",
        "user_id": "user_entity_pk"
      },
      {
        "id": "c22ead7b-33ba-4e25-9330-da72962ffca8",
        "first_name": "Sarah",
        "last_name": "Johnson",
        "email": "sarah.johnson@example.com",
        "created_at": "2023-09-13T07:14:35.581Z",
        "updated_at": "2023-09-14T04:00:38.664Z",
        "company_id": "main_entity_pk",
        "user_id": "user_entity_pk"
      },
      {
        "id": "33a5ef99-22a1-4271-a430-070614e7d495",
        "first_name": "Robert",
        "last_name": "Wilson",
        "email": "robert.wilson@example.com",
        "created_at": "2023-09-13T07:44:50.441Z",
        "updated_at": "2023-09-13T23:14:47.618Z",
        "company_id": "main_entity_pk",
        "user_id": "user_entity_pk"
      }
    ],
    "roqUser": [
      {
        "reference": "9f696e48-320b-44df-985b-b6e2951c5ef8",
        "email": "Jessie.Russel29@yahoo.com",
        "firstName": "Blake",
        "lastName": "Hills",
        "active": true,
        "avatarUrl": "https://avatars.githubusercontent.com/u/21470931",
        "tenantId": null
      },
      {
        "reference": "4ef3f3c3-3f67-46bb-b030-f3c0e537dbbe",
        "email": "Meredith_Wisozk63@gmail.com",
        "firstName": "Valentin",
        "lastName": "Dietrich-Kiehn",
        "active": true,
        "avatarUrl": "https://avatars.githubusercontent.com/u/54599096",
        "tenantId": null
      },
      {
        "reference": "db322d3e-f459-40c3-a384-38ea97178d69",
        "email": "Monserrat25@yahoo.com",
        "firstName": "Tess",
        "lastName": "Wolf",
        "active": true,
        "avatarUrl": "https://avatars.githubusercontent.com/u/38692361",
        "tenantId": null
      },
      {
        "reference": "603a253f-8a11-4bc8-84e8-00997f6993ac",
        "email": "Rosalia_Johns@yahoo.com",
        "firstName": "Ashtyn",
        "lastName": "Kertzmann",
        "active": true,
        "avatarUrl": "https://avatars.githubusercontent.com/u/56079541",
        "tenantId": null
      },
      {
        "reference": "3f40b75a-8213-4315-a065-af9bf2d1fabb",
        "email": "Raphael63@yahoo.com",
        "firstName": "Hildegard",
        "lastName": "Medhurst",
        "active": true,
        "avatarUrl": "https://avatars.githubusercontent.com/u/29323357",
        "tenantId": null
      }
    ]
  },
  {
    "customer": [
      {
        "id": "c1c4fb5c-9140-44a0-8347-b5ad6ad26c3d",
        "first_name": "John",
        "last_name": "Doe",
        "email": "john.doe@example.com",
        "address": "123 Main St",
        "city": "New York",
        "state": "NY",
        "zip_code": "10001",
        "created_at": "2023-09-13T09:34:05.680Z",
        "updated_at": "2023-09-13T17:31:39.005Z",
        "user_id": "user_entity_pk"
      },
      {
        "id": "9606623c-2a7a-4821-ac61-3bc6d8f7e1c0",
        "first_name": "Jane",
        "last_name": "Smith",
        "email": "jane.smith@example.com",
        "address": "456 Elm St",
        "city": "Los Angeles",
        "state": "CA",
        "zip_code": "90001",
        "created_at": "2023-09-13T23:31:25.782Z",
        "updated_at": "2023-09-14T03:54:59.212Z",
        "user_id": "user_entity_pk"
      },
      {
        "id": "3cd1cb3f-a512-425d-89d6-21a8b081eb16",
        "first_name": "Michael",
        "last_name": "Johnson",
        "email": "michael.johnson@example.com",
        "address": "789 Oak St",
        "city": "Chicago",
        "state": "IL",
        "zip_code": "60601",
        "created_at": "2023-09-13T09:03:24.959Z",
        "updated_at": "2023-09-13T23:52:39.466Z",
        "user_id": "user_entity_pk"
      },
      {
        "id": "270eea94-b1d1-4521-b2dd-04c187d211f7",
        "first_name": "Sarah",
        "last_name": "Wilson",
        "email": "sarah.wilson@example.com",
        "address": "321 Pine St",
        "city": "Houston",
        "state": "TX",
        "zip_code": "77001",
        "created_at": "2023-09-13T16:09:21.605Z",
        "updated_at": "2023-09-14T04:06:22.675Z",
        "user_id": "user_entity_pk"
      },
      {
        "id": "878889cd-392e-4a80-b3ca-f760b577611b",
        "first_name": "Robert",
        "last_name": "Brown",
        "email": "robert.brown@example.com",
        "address": "654 Maple St",
        "city": "Phoenix",
        "state": "AZ",
        "zip_code": "85001",
        "created_at": "2023-09-13T05:59:16.507Z",
        "updated_at": "2023-09-14T00:20:57.505Z",
        "user_id": "user_entity_pk"
      }
    ],
    "service": [
      {
        "id": "80e9c4e0-5f28-40da-a574-4879782c10dd",
        "name": "Web Development",
        "description": "Custom web development solutions",
        "price": 87240,
        "duration": 3678,
        "created_at": "2023-09-13T15:52:09.927Z",
        "updated_at": "2023-09-13T12:25:29.292Z",
        "company_id": "main_entity_pk"
      },
      {
        "id": "6eb6e820-40f4-4a69-bc8d-013d21366102",
        "name": "Mobile App Development",
        "description": "Innovative mobile app development services",
        "price": 22876,
        "duration": 4964,
        "created_at": "2023-09-13T15:19:13.948Z",
        "updated_at": "2023-09-13T17:05:44.788Z",
        "company_id": "main_entity_pk"
      },
      {
        "id": "0a4c9eb4-afa1-4439-a1ce-36400610f7f1",
        "name": "Digital Marketing",
        "description": "Effective digital marketing strategies",
        "price": 53973,
        "duration": 54448,
        "created_at": "2023-09-13T20:04:13.972Z",
        "updated_at": "2023-09-13T07:17:22.306Z",
        "company_id": "main_entity_pk"
      },
      {
        "id": "54d6cc66-c081-482b-a42e-1c8057297afa",
        "name": "Cloud Consulting",
        "description": "Expert cloud consulting services",
        "price": 51447,
        "duration": 10746,
        "created_at": "2023-09-13T16:01:37.458Z",
        "updated_at": "2023-09-13T05:47:13.721Z",
        "company_id": "main_entity_pk"
      },
      {
        "id": "3f7b1187-f068-4fd4-9d6f-4464cd8ab6a9",
        "name": "Data Analytics",
        "description": "Advanced data analytics solutions",
        "price": 90661,
        "duration": 48469,
        "created_at": "2023-09-13T13:32:20.461Z",
        "updated_at": "2023-09-13T17:23:04.788Z",
        "company_id": "main_entity_pk"
      }
    ],
    "request": [
      {
        "id": "31bcda19-8869-4880-8779-b335f9bc61f9",
        "status": "Pending",
        "created_at": "2023-09-13T06:23:39.872Z",
        "updated_at": "2023-09-13T09:20:30.690Z",
        "company_id": "main_entity_pk",
        "customer_id": "9606623c-2a7a-4821-ac61-3bc6d8f7e1c0",
        "service_id": "6eb6e820-40f4-4a69-bc8d-013d21366102"
      },
      {
        "id": "fc4e4dc3-e085-4f02-ab11-9b26d0d4aa58",
        "status": "In Progress",
        "created_at": "2023-09-13T10:12:19.760Z",
        "updated_at": "2023-09-14T02:23:00.997Z",
        "company_id": "main_entity_pk",
        "customer_id": "3cd1cb3f-a512-425d-89d6-21a8b081eb16",
        "service_id": "6eb6e820-40f4-4a69-bc8d-013d21366102"
      },
      {
        "id": "6fb60c23-22ab-44ea-af7e-a706b93ae8f1",
        "status": "Completed",
        "created_at": "2023-09-13T10:38:51.442Z",
        "updated_at": "2023-09-13T22:05:21.170Z",
        "company_id": "main_entity_pk",
        "customer_id": "270eea94-b1d1-4521-b2dd-04c187d211f7",
        "service_id": "80e9c4e0-5f28-40da-a574-4879782c10dd"
      },
      {
        "id": "c17c4f5c-0ab5-4612-b252-97fce5b11b7e",
        "status": "Cancelled",
        "created_at": "2023-09-13T21:47:10.330Z",
        "updated_at": "2023-09-13T09:25:46.004Z",
        "company_id": "main_entity_pk",
        "customer_id": "c1c4fb5c-9140-44a0-8347-b5ad6ad26c3d",
        "service_id": "80e9c4e0-5f28-40da-a574-4879782c10dd"
      },
      {
        "id": "5a490eb9-b3f4-4691-85dd-13f3a7f8b330",
        "status": "On Hold",
        "created_at": "2023-09-13T14:34:29.719Z",
        "updated_at": "2023-09-13T16:20:21.146Z",
        "company_id": "main_entity_pk",
        "customer_id": "c1c4fb5c-9140-44a0-8347-b5ad6ad26c3d",
        "service_id": "3f7b1187-f068-4fd4-9d6f-4464cd8ab6a9"
      }
    ],
    "representative": [
      {
        "id": "18b9bdff-936a-456c-9dc3-3d904df5854a",
        "first_name": "John",
        "last_name": "Doe",
        "email": "john.doe@example.com",
        "created_at": "2023-09-14T03:42:05.317Z",
        "updated_at": "2023-09-13T07:07:19.493Z",
        "company_id": "main_entity_pk",
        "user_id": "user_entity_pk"
      },
      {
        "id": "8a7e1d4d-7b71-4eec-9112-90673e088c49",
        "first_name": "Jane",
        "last_name": "Smith",
        "email": "jane.smith@example.com",
        "created_at": "2023-09-13T13:06:31.451Z",
        "updated_at": "2023-09-13T20:37:25.072Z",
        "company_id": "main_entity_pk",
        "user_id": "user_entity_pk"
      },
      {
        "id": "5c42c733-7498-4a8f-bf5c-35974d5b6d86",
        "first_name": "Michael",
        "last_name": "Johnson",
        "email": "michael.johnson@example.com",
        "created_at": "2023-09-13T08:16:51.513Z",
        "updated_at": "2023-09-13T05:26:11.436Z",
        "company_id": "main_entity_pk",
        "user_id": "user_entity_pk"
      },
      {
        "id": "bfb92c67-63ef-474b-8047-64613b17ae46",
        "first_name": "Sarah",
        "last_name": "Wilson",
        "email": "sarah.wilson@example.com",
        "created_at": "2023-09-14T02:43:07.262Z",
        "updated_at": "2023-09-13T04:52:40.068Z",
        "company_id": "main_entity_pk",
        "user_id": "user_entity_pk"
      },
      {
        "id": "905d5d0e-5e9c-4855-b825-762ff7f49186",
        "first_name": "Robert",
        "last_name": "Brown",
        "email": "robert.brown@example.com",
        "created_at": "2023-09-13T16:37:19.333Z",
        "updated_at": "2023-09-13T23:33:50.181Z",
        "company_id": "main_entity_pk",
        "user_id": "user_entity_pk"
      }
    ],
    "roqUser": [
      {
        "reference": "3135e9d3-1990-4d35-ae41-90a1d4327a40",
        "email": "Ceasar40@yahoo.com",
        "firstName": "Damien",
        "lastName": "Schinner-Kozey",
        "active": true,
        "avatarUrl": "https://avatars.githubusercontent.com/u/78044127",
        "tenantId": null
      },
      {
        "reference": "cf4ece6b-12f9-4a60-bb4d-74e5b6ca63a7",
        "email": "Cleve32@gmail.com",
        "firstName": "Randy",
        "lastName": "Reynolds",
        "active": true,
        "avatarUrl": "https://cloudflare-ipfs.com/ipfs/Qmd3W5DuhgHirLHGVixi6V76LhCkZUz6pnFt5AJBiyvHye/avatar/914.jpg",
        "tenantId": null
      },
      {
        "reference": "9993263f-9eef-4bba-a234-8a6cba55a68b",
        "email": "Eldora.Becker1@yahoo.com",
        "firstName": "Cloyd",
        "lastName": "Beier",
        "active": true,
        "avatarUrl": "https://avatars.githubusercontent.com/u/87700114",
        "tenantId": null
      },
      {
        "reference": "affd360f-0cb0-434e-ba5d-ff319cbeaacd",
        "email": "Mariah_Cummings27@yahoo.com",
        "firstName": "Jennyfer",
        "lastName": "Koepp",
        "active": true,
        "avatarUrl": "https://cloudflare-ipfs.com/ipfs/Qmd3W5DuhgHirLHGVixi6V76LhCkZUz6pnFt5AJBiyvHye/avatar/44.jpg",
        "tenantId": null
      },
      {
        "reference": "09381dd6-1c06-4063-912d-ba3b7909a13b",
        "email": "Richmond34@hotmail.com",
        "firstName": "Zola",
        "lastName": "Swift",
        "active": true,
        "avatarUrl": "https://cloudflare-ipfs.com/ipfs/Qmd3W5DuhgHirLHGVixi6V76LhCkZUz6pnFt5AJBiyvHye/avatar/318.jpg",
        "tenantId": null
      }
    ]
  },
  {
    "customer": [
      {
        "id": "7e519a38-4168-4f7e-8541-f93cdb02029b",
        "first_name": "Alice",
        "last_name": "Johnson",
        "email": "alice.johnson@example.com",
        "address": "123 Main St",
        "city": "New York",
        "state": "NY",
        "zip_code": "10001",
        "created_at": "2023-09-13T11:19:52.711Z",
        "updated_at": "2023-09-13T14:36:43.951Z",
        "user_id": "user_entity_pk"
      },
      {
        "id": "d37aabed-d6e8-4aea-9d09-7eaf3d9cd65a",
        "first_name": "David",
        "last_name": "Anderson",
        "email": "david.anderson@example.com",
        "address": "456 Elm St",
        "city": "Los Angeles",
        "state": "CA",
        "zip_code": "90001",
        "created_at": "2023-09-13T15:54:59.397Z",
        "updated_at": "2023-09-13T04:53:49.601Z",
        "user_id": "user_entity_pk"
      },
      {
        "id": "4e159b70-f346-4d8f-b50f-ceff050d87b2",
        "first_name": "Emily",
        "last_name": "Williams",
        "email": "emily.williams@example.com",
        "address": "789 Oak St",
        "city": "Chicago",
        "state": "IL",
        "zip_code": "60601",
        "created_at": "2023-09-13T20:15:58.848Z",
        "updated_at": "2023-09-13T13:51:31.468Z",
        "user_id": "user_entity_pk"
      },
      {
        "id": "8b59753d-4e6a-44ee-9df2-1941ac803c65",
        "first_name": "James",
        "last_name": "Brown",
        "email": "james.brown@example.com",
        "address": "321 Maple St",
        "city": "Houston",
        "state": "TX",
        "zip_code": "77001",
        "created_at": "2023-09-13T12:12:09.008Z",
        "updated_at": "2023-09-13T19:03:59.031Z",
        "user_id": "user_entity_pk"
      },
      {
        "id": "38a8fec6-d24b-4daa-a83b-b98c4b29b067",
        "first_name": "Olivia",
        "last_name": "Smith",
        "email": "olivia.smith@example.com",
        "address": "654 Pine St",
        "city": "Phoenix",
        "state": "AZ",
        "zip_code": "85001",
        "created_at": "2023-09-13T18:09:43.868Z",
        "updated_at": "2023-09-14T00:37:32.775Z",
        "user_id": "user_entity_pk"
      }
    ],
    "service": [
      {
        "id": "83078ea0-d5a3-4796-abff-97cd00da41f9",
        "name": "Web Design",
        "description": "Custom website design and development",
        "price": 30099,
        "duration": 17272,
        "created_at": "2023-09-13T11:27:20.922Z",
        "updated_at": "2023-09-13T17:13:16.024Z",
        "company_id": "main_entity_pk"
      },
      {
        "id": "4b966f25-db0b-4463-8e47-f2b49eeffbd6",
        "name": "Mobile App Development",
        "description": "Creating innovative mobile applications",
        "price": 17949,
        "duration": 49307,
        "created_at": "2023-09-13T22:35:04.751Z",
        "updated_at": "2023-09-13T06:59:25.187Z",
        "company_id": "main_entity_pk"
      },
      {
        "id": "91ad36a7-2890-445d-b082-c30fef34cd7f",
        "name": "Digital Marketing",
        "description": "Driving online growth through targeted marketing strategies",
        "price": 63515,
        "duration": 52024,
        "created_at": "2023-09-13T13:32:34.980Z",
        "updated_at": "2023-09-13T18:04:20.437Z",
        "company_id": "main_entity_pk"
      },
      {
        "id": "c2577156-77b3-4eec-9733-cdeada59278e",
        "name": "Cloud Computing",
        "description": "Leveraging cloud technology for scalable solutions",
        "price": 52283,
        "duration": 49127,
        "created_at": "2023-09-13T07:00:27.170Z",
        "updated_at": "2023-09-13T23:32:46.044Z",
        "company_id": "main_entity_pk"
      },
      {
        "id": "e68240f3-f451-4594-a17d-b063b5d3d936",
        "name": "Data Analytics",
        "description": "Analyzing data to gain valuable insights",
        "price": 72402,
        "duration": 33455,
        "created_at": "2023-09-13T05:59:15.691Z",
        "updated_at": "2023-09-13T21:09:51.607Z",
        "company_id": "main_entity_pk"
      }
    ],
    "request": [
      {
        "id": "18cc2cac-21b7-444e-8316-fddc36707536",
        "status": "Pending",
        "created_at": "2023-09-13T13:43:30.992Z",
        "updated_at": "2023-09-13T18:13:01.511Z",
        "company_id": "main_entity_pk",
        "customer_id": "38a8fec6-d24b-4daa-a83b-b98c4b29b067",
        "service_id": "91ad36a7-2890-445d-b082-c30fef34cd7f"
      },
      {
        "id": "fa9e3e70-26fc-44a6-92de-e3a91f4f3d9f",
        "status": "In Progress",
        "created_at": "2023-09-13T14:35:06.874Z",
        "updated_at": "2023-09-13T06:43:09.887Z",
        "company_id": "main_entity_pk",
        "customer_id": "7e519a38-4168-4f7e-8541-f93cdb02029b",
        "service_id": "e68240f3-f451-4594-a17d-b063b5d3d936"
      },
      {
        "id": "851fc274-e6c1-41b6-843d-e482c780d9e5",
        "status": "Completed",
        "created_at": "2023-09-13T21:24:19.514Z",
        "updated_at": "2023-09-14T02:27:35.587Z",
        "company_id": "main_entity_pk",
        "customer_id": "4e159b70-f346-4d8f-b50f-ceff050d87b2",
        "service_id": "83078ea0-d5a3-4796-abff-97cd00da41f9"
      },
      {
        "id": "127fe085-9684-45d8-9c33-c79873e9bbbb",
        "status": "Cancelled",
        "created_at": "2023-09-13T11:09:33.593Z",
        "updated_at": "2023-09-13T18:18:51.283Z",
        "company_id": "main_entity_pk",
        "customer_id": "d37aabed-d6e8-4aea-9d09-7eaf3d9cd65a",
        "service_id": "91ad36a7-2890-445d-b082-c30fef34cd7f"
      },
      {
        "id": "4f5f18a6-63a7-4d2b-bea7-ea87a5e33c94",
        "status": "On Hold",
        "created_at": "2023-09-14T02:33:42.841Z",
        "updated_at": "2023-09-13T11:10:40.027Z",
        "company_id": "main_entity_pk",
        "customer_id": "4e159b70-f346-4d8f-b50f-ceff050d87b2",
        "service_id": "c2577156-77b3-4eec-9733-cdeada59278e"
      }
    ],
    "representative": [
      {
        "id": "325bc819-6323-4b46-aba8-55cc6ee93da9",
        "first_name": "Alex",
        "last_name": "Johnson",
        "email": "alex.johnson@example.com",
        "created_at": "2023-09-13T05:24:36.201Z",
        "updated_at": "2023-09-13T17:12:03.410Z",
        "company_id": "main_entity_pk",
        "user_id": "user_entity_pk"
      },
      {
        "id": "c0cbff4d-0498-4c61-a84c-9f27ddd0f026",
        "first_name": "Emily",
        "last_name": "Anderson",
        "email": "emily.anderson@example.com",
        "created_at": "2023-09-13T15:09:10.737Z",
        "updated_at": "2023-09-13T14:41:35.092Z",
        "company_id": "main_entity_pk",
        "user_id": "user_entity_pk"
      },
      {
        "id": "fafdc8bd-d5bf-4528-a86b-0eea03b0a979",
        "first_name": "Michael",
        "last_name": "Williams",
        "email": "michael.williams@example.com",
        "created_at": "2023-09-13T05:08:26.922Z",
        "updated_at": "2023-09-13T12:06:45.654Z",
        "company_id": "main_entity_pk",
        "user_id": "user_entity_pk"
      },
      {
        "id": "594658c4-0359-45a8-a9f2-3b4b192d2008",
        "first_name": "Sophia",
        "last_name": "Brown",
        "email": "sophia.brown@example.com",
        "created_at": "2023-09-13T12:47:18.595Z",
        "updated_at": "2023-09-14T04:14:31.507Z",
        "company_id": "main_entity_pk",
        "user_id": "user_entity_pk"
      },
      {
        "id": "0c5e04a6-e6df-490c-80d3-e722de58c9fa",
        "first_name": "Daniel",
        "last_name": "Smith",
        "email": "daniel.smith@example.com",
        "created_at": "2023-09-13T04:23:15.353Z",
        "updated_at": "2023-09-13T21:00:10.661Z",
        "company_id": "main_entity_pk",
        "user_id": "user_entity_pk"
      }
    ],
    "roqUser": [
      {
        "reference": "be5e4c8c-1210-43e3-8644-548b34734a1d",
        "email": "Keeley.Hodkiewicz@hotmail.com",
        "firstName": "Oceane",
        "lastName": "Price",
        "active": true,
        "avatarUrl": "https://cloudflare-ipfs.com/ipfs/Qmd3W5DuhgHirLHGVixi6V76LhCkZUz6pnFt5AJBiyvHye/avatar/14.jpg",
        "tenantId": null
      },
      {
        "reference": "50c63d90-f6ab-4c9d-abfd-6d7dfa2960d0",
        "email": "Laney_Hickle@gmail.com",
        "firstName": "Chelsie",
        "lastName": "Schuster",
        "active": true,
        "avatarUrl": "https://avatars.githubusercontent.com/u/46013171",
        "tenantId": null
      },
      {
        "reference": "ecc683c6-0246-47f0-b1cc-3ac7bc2eac3f",
        "email": "Frida.Casper53@hotmail.com",
        "firstName": "Jada",
        "lastName": "Prosacco",
        "active": true,
        "avatarUrl": "https://avatars.githubusercontent.com/u/20531111",
        "tenantId": null
      },
      {
        "reference": "e53ce9b8-48ac-4325-b856-9708a0b9b2fe",
        "email": "Katherine74@hotmail.com",
        "firstName": "Leila",
        "lastName": "Christiansen",
        "active": true,
        "avatarUrl": "https://cloudflare-ipfs.com/ipfs/Qmd3W5DuhgHirLHGVixi6V76LhCkZUz6pnFt5AJBiyvHye/avatar/834.jpg",
        "tenantId": null
      },
      {
        "reference": "2ca084bb-f9f8-4658-99cb-4e14cfa4957b",
        "email": "Palma_Bechtelar@hotmail.com",
        "firstName": "Alene",
        "lastName": "Haley-D'Amore",
        "active": true,
        "avatarUrl": "https://cloudflare-ipfs.com/ipfs/Qmd3W5DuhgHirLHGVixi6V76LhCkZUz6pnFt5AJBiyvHye/avatar/366.jpg",
        "tenantId": null
      }
    ]
  },
  {
    "customer": [
      {
        "id": "ca19e802-8c45-4764-90bb-27cc5742f331",
        "first_name": "Alice",
        "last_name": "Johnson",
        "email": "alice.johnson@example.com",
        "address": "123 Main St",
        "city": "New York",
        "state": "NY",
        "zip_code": "10001",
        "created_at": "2023-09-14T00:38:40.631Z",
        "updated_at": "2023-09-13T10:14:41.134Z",
        "user_id": "user_entity_pk"
      },
      {
        "id": "63c48334-604b-4f73-b5b6-0479cbf8b071",
        "first_name": "Bob",
        "last_name": "Smith",
        "email": "bob.smith@example.com",
        "address": "456 Elm St",
        "city": "Los Angeles",
        "state": "CA",
        "zip_code": "90001",
        "created_at": "2023-09-13T22:27:34.428Z",
        "updated_at": "2023-09-13T06:38:15.689Z",
        "user_id": "user_entity_pk"
      },
      {
        "id": "aada5c01-2e4b-456f-b31d-0c612d4e2545",
        "first_name": "Eve",
        "last_name": "Brown",
        "email": "eve.brown@example.com",
        "address": "789 Oak St",
        "city": "Chicago",
        "state": "IL",
        "zip_code": "60601",
        "created_at": "2023-09-13T17:17:02.548Z",
        "updated_at": "2023-09-13T09:53:08.776Z",
        "user_id": "user_entity_pk"
      },
      {
        "id": "870147c3-cc1c-4bc8-9ab5-ee2966affe3a",
        "first_name": "David",
        "last_name": "Jones",
        "email": "david.jones@example.com",
        "address": "321 Pine St",
        "city": "Houston",
        "state": "TX",
        "zip_code": "77001",
        "created_at": "2023-09-13T13:09:45.728Z",
        "updated_at": "2023-09-13T21:55:01.885Z",
        "user_id": "user_entity_pk"
      },
      {
        "id": "1730d105-fdf6-4ff4-bc3a-27e3a8fc2d2d",
        "first_name": "Olivia",
        "last_name": "Wilson",
        "email": "olivia.wilson@example.com",
        "address": "654 Maple St",
        "city": "Philadelphia",
        "state": "PA",
        "zip_code": "19101",
        "created_at": "2023-09-14T00:52:50.137Z",
        "updated_at": "2023-09-13T05:25:14.381Z",
        "user_id": "user_entity_pk"
      }
    ],
    "service": [
      {
        "id": "6dac5373-ab18-4206-8d4f-3bd6f0147a6a",
        "name": "Web Development",
        "description": "Custom website development",
        "price": 65495,
        "duration": 21360,
        "created_at": "2023-09-13T19:22:02.187Z",
        "updated_at": "2023-09-13T13:02:32.186Z",
        "company_id": "main_entity_pk"
      },
      {
        "id": "caf7a70e-52c6-47ee-a53b-2af8598a0561",
        "name": "Mobile App Development",
        "description": "iOS and Android app development",
        "price": 67555,
        "duration": 26539,
        "created_at": "2023-09-13T04:21:20.868Z",
        "updated_at": "2023-09-13T18:24:28.511Z",
        "company_id": "main_entity_pk"
      },
      {
        "id": "c4db7e1e-bda7-4712-ac0f-0f7ff624d1c6",
        "name": "Data Analysis",
        "description": "Statistical analysis of data",
        "price": 56096,
        "duration": 6441,
        "created_at": "2023-09-13T10:52:12.522Z",
        "updated_at": "2023-09-13T21:26:16.111Z",
        "company_id": "main_entity_pk"
      },
      {
        "id": "02fcd817-7299-4a9d-bfa1-4ea5cdeabf78",
        "name": "Cloud Computing",
        "description": "Scalable cloud solutions",
        "price": 91661,
        "duration": 11424,
        "created_at": "2023-09-13T23:10:58.559Z",
        "updated_at": "2023-09-13T10:13:05.942Z",
        "company_id": "main_entity_pk"
      },
      {
        "id": "8d310082-ebb8-4cec-bf50-83e70ea45e70",
        "name": "Digital Marketing",
        "description": "Online advertising and SEO",
        "price": 55581,
        "duration": 95542,
        "created_at": "2023-09-13T07:09:23.396Z",
        "updated_at": "2023-09-13T23:15:12.336Z",
        "company_id": "main_entity_pk"
      }
    ],
    "request": [
      {
        "id": "cdc9da36-746f-4aec-9d63-909d98e4ca60",
        "status": "Pending",
        "created_at": "2023-09-13T04:31:59.296Z",
        "updated_at": "2023-09-13T10:25:00.882Z",
        "company_id": "main_entity_pk",
        "customer_id": "1730d105-fdf6-4ff4-bc3a-27e3a8fc2d2d",
        "service_id": "c4db7e1e-bda7-4712-ac0f-0f7ff624d1c6"
      },
      {
        "id": "3474d173-bc47-4f24-b8c1-100442b4bdb7",
        "status": "In Progress",
        "created_at": "2023-09-13T09:06:57.040Z",
        "updated_at": "2023-09-13T12:52:16.418Z",
        "company_id": "main_entity_pk",
        "customer_id": "1730d105-fdf6-4ff4-bc3a-27e3a8fc2d2d",
        "service_id": "02fcd817-7299-4a9d-bfa1-4ea5cdeabf78"
      },
      {
        "id": "64977df3-f0bb-40d7-bd30-584e783c1134",
        "status": "Completed",
        "created_at": "2023-09-13T07:02:07.571Z",
        "updated_at": "2023-09-13T04:59:51.035Z",
        "company_id": "main_entity_pk",
        "customer_id": "ca19e802-8c45-4764-90bb-27cc5742f331",
        "service_id": "c4db7e1e-bda7-4712-ac0f-0f7ff624d1c6"
      },
      {
        "id": "20d3569d-64e7-4913-99dc-da0be9693545",
        "status": "On Hold",
        "created_at": "2023-09-13T09:05:31.333Z",
        "updated_at": "2023-09-13T11:17:31.542Z",
        "company_id": "main_entity_pk",
        "customer_id": "aada5c01-2e4b-456f-b31d-0c612d4e2545",
        "service_id": "8d310082-ebb8-4cec-bf50-83e70ea45e70"
      },
      {
        "id": "a60f224c-7847-4f44-97cf-913d8cdcba79",
        "status": "Cancelled",
        "created_at": "2023-09-14T03:34:32.879Z",
        "updated_at": "2023-09-14T03:23:51.485Z",
        "company_id": "main_entity_pk",
        "customer_id": "ca19e802-8c45-4764-90bb-27cc5742f331",
        "service_id": "02fcd817-7299-4a9d-bfa1-4ea5cdeabf78"
      }
    ],
    "representative": [
      {
        "id": "c6a8f469-6149-42d9-b5c3-12e6006693f0",
        "first_name": "Emily",
        "last_name": "Johnson",
        "email": "emily.johnson@example.com",
        "created_at": "2023-09-14T00:43:38.991Z",
        "updated_at": "2023-09-13T16:08:13.998Z",
        "company_id": "main_entity_pk",
        "user_id": "user_entity_pk"
      },
      {
        "id": "950e0628-692a-49b0-989e-f5b5a83601ea",
        "first_name": "Daniel",
        "last_name": "Smith",
        "email": "daniel.smith@example.com",
        "created_at": "2023-09-13T16:05:46.035Z",
        "updated_at": "2023-09-13T14:09:29.408Z",
        "company_id": "main_entity_pk",
        "user_id": "user_entity_pk"
      },
      {
        "id": "ab39cd2c-49a5-4a9d-a361-a161b459409e",
        "first_name": "Sophia",
        "last_name": "Brown",
        "email": "sophia.brown@example.com",
        "created_at": "2023-09-13T19:24:02.949Z",
        "updated_at": "2023-09-13T22:01:15.450Z",
        "company_id": "main_entity_pk",
        "user_id": "user_entity_pk"
      },
      {
        "id": "50f6f08c-61df-4f73-a463-0a7787c1b3dc",
        "first_name": "Matthew",
        "last_name": "Jones",
        "email": "matthew.jones@example.com",
        "created_at": "2023-09-14T04:19:08.846Z",
        "updated_at": "2023-09-13T04:48:36.666Z",
        "company_id": "main_entity_pk",
        "user_id": "user_entity_pk"
      },
      {
        "id": "816be551-f804-44c1-9703-508d21850df4",
        "first_name": "Olivia",
        "last_name": "Wilson",
        "email": "olivia.wilson@example.com",
        "created_at": "2023-09-14T03:26:39.430Z",
        "updated_at": "2023-09-14T04:17:04.213Z",
        "company_id": "main_entity_pk",
        "user_id": "user_entity_pk"
      }
    ],
    "roqUser": [
      {
        "reference": "28f1928d-f53c-4d76-be59-30555c129705",
        "email": "Ian_Homenick56@gmail.com",
        "firstName": "Halie",
        "lastName": "Flatley",
        "active": true,
        "avatarUrl": "https://cloudflare-ipfs.com/ipfs/Qmd3W5DuhgHirLHGVixi6V76LhCkZUz6pnFt5AJBiyvHye/avatar/963.jpg",
        "tenantId": null
      },
      {
        "reference": "311cdb0b-28a4-4476-91ea-060bc226a612",
        "email": "Molly_Schowalter55@yahoo.com",
        "firstName": "Adonis",
        "lastName": "Steuber",
        "active": true,
        "avatarUrl": "https://cloudflare-ipfs.com/ipfs/Qmd3W5DuhgHirLHGVixi6V76LhCkZUz6pnFt5AJBiyvHye/avatar/1104.jpg",
        "tenantId": null
      },
      {
        "reference": "87cf3c0d-444f-4839-802e-d38f1a0925da",
        "email": "Mustafa_Lesch@yahoo.com",
        "firstName": "Shirley",
        "lastName": "Mohr",
        "active": true,
        "avatarUrl": "https://cloudflare-ipfs.com/ipfs/Qmd3W5DuhgHirLHGVixi6V76LhCkZUz6pnFt5AJBiyvHye/avatar/1069.jpg",
        "tenantId": null
      },
      {
        "reference": "8f3bc127-d0c8-4777-9612-72c0f3f5ae8e",
        "email": "Justyn_Kessler5@hotmail.com",
        "firstName": "Lelah",
        "lastName": "O'Connell-Koss",
        "active": true,
        "avatarUrl": "https://avatars.githubusercontent.com/u/42983483",
        "tenantId": null
      },
      {
        "reference": "c278b9e4-344f-4b91-8b7c-ba24fa8d4e6a",
        "email": "Maryam51@hotmail.com",
        "firstName": "Hazel",
        "lastName": "Stiedemann",
        "active": true,
        "avatarUrl": "https://avatars.githubusercontent.com/u/12781233",
        "tenantId": null
      }
    ]
  },
  {
    "customer": [
      {
        "id": "4de98aa7-4fdf-4d47-a5a7-f148656f4b3c",
        "first_name": "Alice",
        "last_name": "Adams",
        "email": "alice.adams@example.com",
        "address": "123 Main St",
        "city": "New York",
        "state": "NY",
        "zip_code": "10001",
        "created_at": "2023-09-13T22:07:59.604Z",
        "updated_at": "2023-09-13T09:26:38.975Z",
        "user_id": "user_entity_pk"
      },
      {
        "id": "f2d999cc-8e21-4fb5-923f-086c600be32f",
        "first_name": "Bob",
        "last_name": "Baker",
        "email": "bob.baker@example.com",
        "address": "456 Elm St",
        "city": "Los Angeles",
        "state": "CA",
        "zip_code": "90001",
        "created_at": "2023-09-13T14:13:15.226Z",
        "updated_at": "2023-09-13T07:45:18.264Z",
        "user_id": "user_entity_pk"
      },
      {
        "id": "26b22d7b-0ffa-418a-80fb-6d4abfe7ba8a",
        "first_name": "Eve",
        "last_name": "Clark",
        "email": "eve.clark@example.com",
        "address": "789 Oak St",
        "city": "Chicago",
        "state": "IL",
        "zip_code": "60601",
        "created_at": "2023-09-14T03:45:49.020Z",
        "updated_at": "2023-09-13T09:45:19.395Z",
        "user_id": "user_entity_pk"
      },
      {
        "id": "b270f5b7-75a3-4e02-83d8-d18f384ffd43",
        "first_name": "Charlie",
        "last_name": "Davis",
        "email": "charlie.davis@example.com",
        "address": "321 Pine St",
        "city": "Houston",
        "state": "TX",
        "zip_code": "77001",
        "created_at": "2023-09-14T00:37:29.380Z",
        "updated_at": "2023-09-13T20:41:57.515Z",
        "user_id": "user_entity_pk"
      },
      {
        "id": "800af5b7-f299-4dad-a546-45c89bee521a",
        "first_name": "Grace",
        "last_name": "Evans",
        "email": "grace.evans@example.com",
        "address": "654 Maple St",
        "city": "Phoenix",
        "state": "AZ",
        "zip_code": "85001",
        "created_at": "2023-09-13T07:03:19.403Z",
        "updated_at": "2023-09-13T20:30:27.147Z",
        "user_id": "user_entity_pk"
      }
    ],
    "service": [
      {
        "id": "6a7e22dc-7f4a-432a-b3e8-96e4e2d7792a",
        "name": "Web Development",
        "description": "Custom web development solutions",
        "price": 88458,
        "duration": 86626,
        "created_at": "2023-09-13T23:45:43.872Z",
        "updated_at": "2023-09-13T12:11:27.618Z",
        "company_id": "main_entity_pk"
      },
      {
        "id": "4f96e0c4-2fec-4420-a23b-d673e90b1d9a",
        "name": "Mobile App Development",
        "description": "Innovative mobile app development services",
        "price": 92236,
        "duration": 33553,
        "created_at": "2023-09-13T17:54:19.360Z",
        "updated_at": "2023-09-13T17:42:14.047Z",
        "company_id": "main_entity_pk"
      },
      {
        "id": "7c5c7d59-d84a-4e37-bf5e-07f2e57e26c6",
        "name": "Data Analysis",
        "description": "Advanced data analysis techniques",
        "price": 69237,
        "duration": 14142,
        "created_at": "2023-09-13T09:52:23.027Z",
        "updated_at": "2023-09-13T08:36:54.386Z",
        "company_id": "main_entity_pk"
      },
      {
        "id": "7dcbc68d-d1a9-420c-9676-7c7061275b5e",
        "name": "Cloud Consulting",
        "description": "Expert cloud consulting services",
        "price": 8542,
        "duration": 26370,
        "created_at": "2023-09-14T01:53:33.960Z",
        "updated_at": "2023-09-13T23:20:16.951Z",
        "company_id": "main_entity_pk"
      },
      {
        "id": "59ff6121-53b9-402d-b281-8a599e235425",
        "name": "UI/UX Design",
        "description": "Creative UI/UX design solutions",
        "price": 19670,
        "duration": 86808,
        "created_at": "2023-09-13T19:05:14.728Z",
        "updated_at": "2023-09-13T20:09:09.915Z",
        "company_id": "main_entity_pk"
      }
    ],
    "request": [
      {
        "id": "8fcca9d5-a693-444f-a513-18993aacf1cd",
        "status": "Pending",
        "created_at": "2023-09-13T20:55:21.980Z",
        "updated_at": "2023-09-13T04:47:38.829Z",
        "company_id": "main_entity_pk",
        "customer_id": "4de98aa7-4fdf-4d47-a5a7-f148656f4b3c",
        "service_id": "7c5c7d59-d84a-4e37-bf5e-07f2e57e26c6"
      },
      {
        "id": "23266d06-9d01-4c29-89fa-294d711526c2",
        "status": "In Progress",
        "created_at": "2023-09-13T21:36:56.694Z",
        "updated_at": "2023-09-13T18:57:59.759Z",
        "company_id": "main_entity_pk",
        "customer_id": "26b22d7b-0ffa-418a-80fb-6d4abfe7ba8a",
        "service_id": "6a7e22dc-7f4a-432a-b3e8-96e4e2d7792a"
      },
      {
        "id": "659f55a9-d2ca-418f-9d28-041dac744c78",
        "status": "Completed",
        "created_at": "2023-09-13T10:05:17.211Z",
        "updated_at": "2023-09-13T22:23:45.608Z",
        "company_id": "main_entity_pk",
        "customer_id": "4de98aa7-4fdf-4d47-a5a7-f148656f4b3c",
        "service_id": "7c5c7d59-d84a-4e37-bf5e-07f2e57e26c6"
      },
      {
        "id": "fc7b5c9b-4743-4b64-a6df-445892ebc5a7",
        "status": "Cancelled",
        "created_at": "2023-09-13T12:35:06.192Z",
        "updated_at": "2023-09-13T18:44:43.007Z",
        "company_id": "main_entity_pk",
        "customer_id": "800af5b7-f299-4dad-a546-45c89bee521a",
        "service_id": "4f96e0c4-2fec-4420-a23b-d673e90b1d9a"
      },
      {
        "id": "227137cb-3158-47a8-aedc-bd68562ba6a3",
        "status": "On Hold",
        "created_at": "2023-09-13T07:01:06.154Z",
        "updated_at": "2023-09-14T03:10:03.208Z",
        "company_id": "main_entity_pk",
        "customer_id": "26b22d7b-0ffa-418a-80fb-6d4abfe7ba8a",
        "service_id": "7c5c7d59-d84a-4e37-bf5e-07f2e57e26c6"
      }
    ],
    "representative": [
      {
        "id": "c87d7c6a-1a13-4fa9-b88e-2ff91721716a",
        "first_name": "Emily",
        "last_name": "Smith",
        "email": "emily.smith@example.com",
        "created_at": "2023-09-13T16:12:59.432Z",
        "updated_at": "2023-09-14T01:53:46.638Z",
        "company_id": "main_entity_pk",
        "user_id": "user_entity_pk"
      },
      {
        "id": "b6d0ef39-9997-42d7-91ff-c00d92f27fd2",
        "first_name": "James",
        "last_name": "Johnson",
        "email": "james.johnson@example.com",
        "created_at": "2023-09-13T20:14:55.288Z",
        "updated_at": "2023-09-13T23:25:40.459Z",
        "company_id": "main_entity_pk",
        "user_id": "user_entity_pk"
      },
      {
        "id": "c89dddcf-cd58-4455-95b6-92640b526346",
        "first_name": "Olivia",
        "last_name": "Brown",
        "email": "olivia.brown@example.com",
        "created_at": "2023-09-13T23:34:26.570Z",
        "updated_at": "2023-09-13T05:30:08.246Z",
        "company_id": "main_entity_pk",
        "user_id": "user_entity_pk"
      },
      {
        "id": "2ac6a5c5-a148-41bd-94eb-e8646754056e",
        "first_name": "William",
        "last_name": "Taylor",
        "email": "william.taylor@example.com",
        "created_at": "2023-09-13T21:41:39.393Z",
        "updated_at": "2023-09-13T12:06:58.071Z",
        "company_id": "main_entity_pk",
        "user_id": "user_entity_pk"
      },
      {
        "id": "72317a00-6da4-4601-aab9-c6caa2c556f4",
        "first_name": "Sophia",
        "last_name": "Miller",
        "email": "sophia.miller@example.com",
        "created_at": "2023-09-13T07:44:23.809Z",
        "updated_at": "2023-09-13T14:03:49.334Z",
        "company_id": "main_entity_pk",
        "user_id": "user_entity_pk"
      }
    ],
    "roqUser": [
      {
        "reference": "c79357bb-4ed9-4165-921a-2b084171965e",
        "email": "Willis.Mohr@gmail.com",
        "firstName": "Howell",
        "lastName": "Davis",
        "active": true,
        "avatarUrl": "https://cloudflare-ipfs.com/ipfs/Qmd3W5DuhgHirLHGVixi6V76LhCkZUz6pnFt5AJBiyvHye/avatar/843.jpg",
        "tenantId": null
      },
      {
        "reference": "bb260db0-7c32-4a14-9667-5e68fb248236",
        "email": "Lorenza_Klein@yahoo.com",
        "firstName": "Freida",
        "lastName": "Marks",
        "active": true,
        "avatarUrl": "https://avatars.githubusercontent.com/u/70726680",
        "tenantId": null
      },
      {
        "reference": "9a49bc7c-676f-471c-863d-46a0e77134a3",
        "email": "Ayden69@gmail.com",
        "firstName": "Emelie",
        "lastName": "Volkman",
        "active": true,
        "avatarUrl": "https://cloudflare-ipfs.com/ipfs/Qmd3W5DuhgHirLHGVixi6V76LhCkZUz6pnFt5AJBiyvHye/avatar/892.jpg",
        "tenantId": null
      },
      {
        "reference": "016055df-c62f-4ae3-a4bb-aa51f4e89b36",
        "email": "Isaias_Klein37@hotmail.com",
        "firstName": "Joannie",
        "lastName": "Bailey",
        "active": true,
        "avatarUrl": "https://avatars.githubusercontent.com/u/14143814",
        "tenantId": null
      },
      {
        "reference": "de7e95f2-0195-4fb6-ba17-91f7ae4846ff",
        "email": "Justen86@yahoo.com",
        "firstName": "Seth",
        "lastName": "Christiansen",
        "active": true,
        "avatarUrl": "https://cloudflare-ipfs.com/ipfs/Qmd3W5DuhgHirLHGVixi6V76LhCkZUz6pnFt5AJBiyvHye/avatar/1234.jpg",
        "tenantId": null
      }
    ]
  },
  {
    "customer": [
      {
        "id": "19ea4d88-7502-48bc-9449-7755d3c49dd0",
        "first_name": "Alice",
        "last_name": "Anderson",
        "email": "alice.anderson@example.com",
        "address": "123 Main St",
        "city": "New York",
        "state": "NY",
        "zip_code": "10001",
        "created_at": "2023-09-13T21:28:10.887Z",
        "updated_at": "2023-09-13T15:28:52.491Z",
        "user_id": "user_entity_pk"
      },
      {
        "id": "45b3ed6f-853b-48cd-b283-830d6ab1ad53",
        "first_name": "Bob",
        "last_name": "Baker",
        "email": "bob.baker@example.com",
        "address": "456 Elm St",
        "city": "Los Angeles",
        "state": "CA",
        "zip_code": "90001",
        "created_at": "2023-09-14T04:02:13.150Z",
        "updated_at": "2023-09-14T01:50:09.310Z",
        "user_id": "user_entity_pk"
      },
      {
        "id": "80378fae-e7d2-41e1-9e56-c84a7e641ef7",
        "first_name": "Eve",
        "last_name": "Evans",
        "email": "eve.evans@example.com",
        "address": "789 Oak St",
        "city": "Chicago",
        "state": "IL",
        "zip_code": "60601",
        "created_at": "2023-09-13T09:07:52.989Z",
        "updated_at": "2023-09-13T07:45:31.541Z",
        "user_id": "user_entity_pk"
      },
      {
        "id": "4c55e4d3-80c0-41e0-bbbf-a5bd323cece4",
        "first_name": "Charlie",
        "last_name": "Cooper",
        "email": "charlie.cooper@example.com",
        "address": "321 Pine St",
        "city": "Houston",
        "state": "TX",
        "zip_code": "77001",
        "created_at": "2023-09-13T10:11:41.366Z",
        "updated_at": "2023-09-13T18:25:05.297Z",
        "user_id": "user_entity_pk"
      },
      {
        "id": "9d06da85-878a-4895-ad94-8d2329c9f351",
        "first_name": "Grace",
        "last_name": "Green",
        "email": "grace.green@example.com",
        "address": "654 Maple St",
        "city": "Phoenix",
        "state": "AZ",
        "zip_code": "85001",
        "created_at": "2023-09-13T15:28:06.836Z",
        "updated_at": "2023-09-14T03:54:28.285Z",
        "user_id": "user_entity_pk"
      }
    ],
    "service": [
      {
        "id": "03a40d9a-9e6f-4b80-b6d8-0f85bc851231",
        "name": "Web Design",
        "description": "Professional website design services",
        "price": 33461,
        "duration": 88626,
        "created_at": "2023-09-13T11:42:43.572Z",
        "updated_at": "2023-09-13T11:32:06.180Z",
        "company_id": "main_entity_pk"
      },
      {
        "id": "5d2f3206-c9a3-44c8-8dad-34fbb053854a",
        "name": "Mobile App Development",
        "description": "Custom mobile app development solutions",
        "price": 69753,
        "duration": 19648,
        "created_at": "2023-09-13T15:52:14.166Z",
        "updated_at": "2023-09-14T02:51:12.600Z",
        "company_id": "main_entity_pk"
      },
      {
        "id": "96a04125-f0c4-4567-ad0a-4636d0ee4af0",
        "name": "Digital Marketing",
        "description": "Effective digital marketing strategies",
        "price": 94168,
        "duration": 56824,
        "created_at": "2023-09-13T14:42:10.346Z",
        "updated_at": "2023-09-13T17:35:27.078Z",
        "company_id": "main_entity_pk"
      },
      {
        "id": "f1f1c0d3-f96d-4297-a653-3b43db9d27b3",
        "name": "Cloud Computing",
        "description": "Scalable cloud computing solutions",
        "price": 56453,
        "duration": 79151,
        "created_at": "2023-09-14T00:39:44.923Z",
        "updated_at": "2023-09-14T03:18:22.388Z",
        "company_id": "main_entity_pk"
      },
      {
        "id": "5c927823-643f-4719-8d92-34df000f85ba",
        "name": "Data Analytics",
        "description": "Insightful data analytics services",
        "price": 49681,
        "duration": 38423,
        "created_at": "2023-09-14T00:02:10.821Z",
        "updated_at": "2023-09-14T03:11:42.505Z",
        "company_id": "main_entity_pk"
      }
    ],
    "request": [
      {
        "id": "449f9942-6dae-4ad4-8885-405803daff11",
        "status": "Pending",
        "created_at": "2023-09-13T10:44:34.542Z",
        "updated_at": "2023-09-13T14:15:39.357Z",
        "company_id": "main_entity_pk",
        "customer_id": "80378fae-e7d2-41e1-9e56-c84a7e641ef7",
        "service_id": "96a04125-f0c4-4567-ad0a-4636d0ee4af0"
      },
      {
        "id": "95870fe2-bc4b-4a51-8192-812921898fb0",
        "status": "In Progress",
        "created_at": "2023-09-13T10:44:17.748Z",
        "updated_at": "2023-09-13T05:30:52.611Z",
        "company_id": "main_entity_pk",
        "customer_id": "4c55e4d3-80c0-41e0-bbbf-a5bd323cece4",
        "service_id": "03a40d9a-9e6f-4b80-b6d8-0f85bc851231"
      },
      {
        "id": "0965da36-5c80-4819-a800-e8880059163d",
        "status": "Completed",
        "created_at": "2023-09-14T00:05:47.574Z",
        "updated_at": "2023-09-13T23:33:02.650Z",
        "company_id": "main_entity_pk",
        "customer_id": "9d06da85-878a-4895-ad94-8d2329c9f351",
        "service_id": "f1f1c0d3-f96d-4297-a653-3b43db9d27b3"
      },
      {
        "id": "e211aade-4716-4dde-960f-0a44badd403d",
        "status": "Cancelled",
        "created_at": "2023-09-13T09:40:44.384Z",
        "updated_at": "2023-09-13T22:59:50.957Z",
        "company_id": "main_entity_pk",
        "customer_id": "19ea4d88-7502-48bc-9449-7755d3c49dd0",
        "service_id": "5c927823-643f-4719-8d92-34df000f85ba"
      },
      {
        "id": "91dc209c-87f7-4b6b-b44b-fbe2f6ebb945",
        "status": "On Hold",
        "created_at": "2023-09-13T14:09:02.561Z",
        "updated_at": "2023-09-13T10:45:41.544Z",
        "company_id": "main_entity_pk",
        "customer_id": "19ea4d88-7502-48bc-9449-7755d3c49dd0",
        "service_id": "96a04125-f0c4-4567-ad0a-4636d0ee4af0"
      }
    ],
    "representative": [
      {
        "id": "ed4db53d-cce2-4ecc-8ab0-2f708ed7ce4a",
        "first_name": "Emily",
        "last_name": "Johnson",
        "email": "emily.johnson@example.com",
        "created_at": "2023-09-13T22:14:49.039Z",
        "updated_at": "2023-09-14T00:24:04.617Z",
        "company_id": "main_entity_pk",
        "user_id": "user_entity_pk"
      },
      {
        "id": "06acc8fa-4c46-4122-b221-4780ff6bf061",
        "first_name": "James",
        "last_name": "Smith",
        "email": "james.smith@example.com",
        "created_at": "2023-09-13T19:55:31.613Z",
        "updated_at": "2023-09-13T22:49:48.288Z",
        "company_id": "main_entity_pk",
        "user_id": "user_entity_pk"
      },
      {
        "id": "e0c1d057-1679-4c35-87c6-b0bea24de356",
        "first_name": "Olivia",
        "last_name": "Brown",
        "email": "olivia.brown@example.com",
        "created_at": "2023-09-13T16:23:34.573Z",
        "updated_at": "2023-09-13T22:04:57.923Z",
        "company_id": "main_entity_pk",
        "user_id": "user_entity_pk"
      },
      {
        "id": "82b6124e-ba16-4d1c-844e-ed7b31954608",
        "first_name": "Daniel",
        "last_name": "Taylor",
        "email": "daniel.taylor@example.com",
        "created_at": "2023-09-13T11:02:41.450Z",
        "updated_at": "2023-09-13T23:55:04.869Z",
        "company_id": "main_entity_pk",
        "user_id": "user_entity_pk"
      },
      {
        "id": "52b51e62-a640-4368-b92a-edc6cf65c571",
        "first_name": "Sophia",
        "last_name": "Anderson",
        "email": "sophia.anderson@example.com",
        "created_at": "2023-09-13T08:34:05.642Z",
        "updated_at": "2023-09-14T01:52:38.168Z",
        "company_id": "main_entity_pk",
        "user_id": "user_entity_pk"
      }
    ],
    "roqUser": [
      {
        "reference": "7fc815c5-b309-4474-872d-b1d3f8ea7481",
        "email": "Rodrigo5@hotmail.com",
        "firstName": "Ayla",
        "lastName": "Langworth",
        "active": true,
        "avatarUrl": "https://avatars.githubusercontent.com/u/19505116",
        "tenantId": null
      },
      {
        "reference": "422336fb-c097-4b92-9eeb-fa8e8a596f66",
        "email": "Joaquin41@gmail.com",
        "firstName": "Laila",
        "lastName": "Kertzmann",
        "active": true,
        "avatarUrl": "https://cloudflare-ipfs.com/ipfs/Qmd3W5DuhgHirLHGVixi6V76LhCkZUz6pnFt5AJBiyvHye/avatar/1064.jpg",
        "tenantId": null
      },
      {
        "reference": "1043fec9-5369-4494-986c-ce8bd002c67a",
        "email": "Lauryn21@yahoo.com",
        "firstName": "Jamey",
        "lastName": "Grady",
        "active": true,
        "avatarUrl": "https://avatars.githubusercontent.com/u/43046429",
        "tenantId": null
      },
      {
        "reference": "b2ba8438-3a46-46c8-9cad-7750d8ac6bf3",
        "email": "Sigmund99@hotmail.com",
        "firstName": "Ebony",
        "lastName": "Hackett",
        "active": true,
        "avatarUrl": "https://avatars.githubusercontent.com/u/83055097",
        "tenantId": null
      },
      {
        "reference": "319b27cb-79d9-4150-ac24-9e01d4287ee8",
        "email": "Liam.Homenick@gmail.com",
        "firstName": "Tessie",
        "lastName": "Osinski",
        "active": true,
        "avatarUrl": "https://cloudflare-ipfs.com/ipfs/Qmd3W5DuhgHirLHGVixi6V76LhCkZUz6pnFt5AJBiyvHye/avatar/991.jpg",
        "tenantId": null
      }
    ]
  },
  {
    "customer": [
      {
        "id": "722b9763-f1b0-43b7-8af3-d00e8b36e280",
        "first_name": "John",
        "last_name": "Doe",
        "email": "john.doe@example.com",
        "address": "123 Main St",
        "city": "New York",
        "state": "NY",
        "zip_code": "10001",
        "created_at": "2023-09-13T22:50:52.715Z",
        "updated_at": "2023-09-13T10:38:47.796Z",
        "user_id": "user_entity_pk"
      },
      {
        "id": "baadb857-db3b-499e-96eb-4cb5521e3347",
        "first_name": "Jane",
        "last_name": "Smith",
        "email": "jane.smith@example.com",
        "address": "456 Elm St",
        "city": "Los Angeles",
        "state": "CA",
        "zip_code": "90001",
        "created_at": "2023-09-13T08:38:18.941Z",
        "updated_at": "2023-09-14T02:53:42.486Z",
        "user_id": "user_entity_pk"
      },
      {
        "id": "373a4123-107d-4e80-ba16-719daf8356ab",
        "first_name": "Michael",
        "last_name": "Brown",
        "email": "michael.brown@example.com",
        "address": "789 Oak St",
        "city": "Chicago",
        "state": "IL",
        "zip_code": "60601",
        "created_at": "2023-09-13T13:51:21.289Z",
        "updated_at": "2023-09-13T16:05:25.593Z",
        "user_id": "user_entity_pk"
      },
      {
        "id": "546ee344-8079-42c4-afca-ea478fa5bf26",
        "first_name": "Sarah",
        "last_name": "Johnson",
        "email": "sarah.johnson@example.com",
        "address": "321 Pine St",
        "city": "Houston",
        "state": "TX",
        "zip_code": "77001",
        "created_at": "2023-09-13T22:06:54.718Z",
        "updated_at": "2023-09-13T21:04:04.230Z",
        "user_id": "user_entity_pk"
      },
      {
        "id": "285a602e-1880-40c3-96d2-ef3205e47f8c",
        "first_name": "Robert",
        "last_name": "Wilson",
        "email": "robert.wilson@example.com",
        "address": "654 Maple St",
        "city": "Phoenix",
        "state": "AZ",
        "zip_code": "85001",
        "created_at": "2023-09-14T03:04:16.378Z",
        "updated_at": "2023-09-13T13:28:44.763Z",
        "user_id": "user_entity_pk"
      }
    ],
    "service": [
      {
        "id": "e4b55943-fc8e-4f30-ad6b-cdaae1b50f3c",
        "name": "Web Development",
        "description": "Professional website development services",
        "price": 84320,
        "duration": 8365,
        "created_at": "2023-09-14T04:11:47.550Z",
        "updated_at": "2023-09-13T17:10:38.030Z",
        "company_id": "main_entity_pk"
      },
      {
        "id": "9d7f233f-291b-41f8-93b3-0b8b21c013a0",
        "name": "Graphic Design",
        "description": "Creative graphic design solutions",
        "price": 4164,
        "duration": 12544,
        "created_at": "2023-09-13T12:05:03.159Z",
        "updated_at": "2023-09-13T10:04:23.967Z",
        "company_id": "main_entity_pk"
      },
      {
        "id": "748ab612-8bba-4498-a4ab-959dfe1f05ea",
        "name": "Marketing Consulting",
        "description": "Expert marketing consulting for businesses",
        "price": 56977,
        "duration": 58370,
        "created_at": "2023-09-13T16:08:44.458Z",
        "updated_at": "2023-09-13T19:44:38.179Z",
        "company_id": "main_entity_pk"
      },
      {
        "id": "a2798898-4e61-4d37-bd26-f336acde0d60",
        "name": "IT Support",
        "description": "Reliable IT support for organizations",
        "price": 84040,
        "duration": 83100,
        "created_at": "2023-09-13T18:20:05.039Z",
        "updated_at": "2023-09-13T11:49:03.612Z",
        "company_id": "main_entity_pk"
      },
      {
        "id": "ca16d420-c7b5-47ad-b6b6-35a86f4fbec7",
        "name": "Social Media Management",
        "description": "Effective social media management strategies",
        "price": 71370,
        "duration": 29009,
        "created_at": "2023-09-14T01:53:44.366Z",
        "updated_at": "2023-09-13T13:27:38.733Z",
        "company_id": "main_entity_pk"
      }
    ],
    "request": [
      {
        "id": "947fd4fb-2f37-4a6a-9a2e-561e9dfacd04",
        "status": "Pending",
        "created_at": "2023-09-13T04:56:31.362Z",
        "updated_at": "2023-09-13T12:28:37.660Z",
        "company_id": "main_entity_pk",
        "customer_id": "373a4123-107d-4e80-ba16-719daf8356ab",
        "service_id": "e4b55943-fc8e-4f30-ad6b-cdaae1b50f3c"
      },
      {
        "id": "8dfe53eb-1703-41f4-9c07-d5343dcb5199",
        "status": "In Progress",
        "created_at": "2023-09-13T13:49:17.193Z",
        "updated_at": "2023-09-14T04:08:48.013Z",
        "company_id": "main_entity_pk",
        "customer_id": "285a602e-1880-40c3-96d2-ef3205e47f8c",
        "service_id": "748ab612-8bba-4498-a4ab-959dfe1f05ea"
      },
      {
        "id": "ee5a5ad1-5d6e-447b-84a0-961ecd633cd2",
        "status": "Completed",
        "created_at": "2023-09-13T11:54:03.614Z",
        "updated_at": "2023-09-13T19:56:30.103Z",
        "company_id": "main_entity_pk",
        "customer_id": "546ee344-8079-42c4-afca-ea478fa5bf26",
        "service_id": "9d7f233f-291b-41f8-93b3-0b8b21c013a0"
      },
      {
        "id": "b3bc186f-8f01-40ea-a4e4-739941a5ba2e",
        "status": "Cancelled",
        "created_at": "2023-09-13T06:16:41.026Z",
        "updated_at": "2023-09-13T16:46:31.353Z",
        "company_id": "main_entity_pk",
        "customer_id": "373a4123-107d-4e80-ba16-719daf8356ab",
        "service_id": "ca16d420-c7b5-47ad-b6b6-35a86f4fbec7"
      },
      {
        "id": "d40c2926-d632-4849-af8e-bef03f04660c",
        "status": "On Hold",
        "created_at": "2023-09-13T07:14:00.818Z",
        "updated_at": "2023-09-13T15:34:53.227Z",
        "company_id": "main_entity_pk",
        "customer_id": "baadb857-db3b-499e-96eb-4cb5521e3347",
        "service_id": "ca16d420-c7b5-47ad-b6b6-35a86f4fbec7"
      }
    ],
    "representative": [
      {
        "id": "f0db6c26-de36-4423-8225-3e805fc3fabc",
        "first_name": "John",
        "last_name": "Doe",
        "email": "john.doe@example.com",
        "created_at": "2023-09-13T17:45:14.732Z",
        "updated_at": "2023-09-13T23:39:56.536Z",
        "company_id": "main_entity_pk",
        "user_id": "user_entity_pk"
      },
      {
        "id": "e541c36d-8cec-4201-9d0c-ecffad0b76d3",
        "first_name": "Jane",
        "last_name": "Smith",
        "email": "jane.smith@example.com",
        "created_at": "2023-09-13T06:58:33.901Z",
        "updated_at": "2023-09-14T02:07:53.143Z",
        "company_id": "main_entity_pk",
        "user_id": "user_entity_pk"
      },
      {
        "id": "4711c5aa-07ad-435d-a1dc-b44f2a1a33ad",
        "first_name": "Michael",
        "last_name": "Brown",
        "email": "michael.brown@example.com",
        "created_at": "2023-09-13T19:42:42.536Z",
        "updated_at": "2023-09-13T13:09:26.361Z",
        "company_id": "main_entity_pk",
        "user_id": "user_entity_pk"
      },
      {
        "id": "839b4fa5-5dc5-48ec-9db0-5f5bbd52c1ae",
        "first_name": "Sarah",
        "last_name": "Johnson",
        "email": "sarah.johnson@example.com",
        "created_at": "2023-09-14T02:47:54.048Z",
        "updated_at": "2023-09-14T01:35:31.144Z",
        "company_id": "main_entity_pk",
        "user_id": "user_entity_pk"
      },
      {
        "id": "c4b6ce9d-80a8-4365-b700-aeab055c603f",
        "first_name": "Robert",
        "last_name": "Wilson",
        "email": "robert.wilson@example.com",
        "created_at": "2023-09-13T22:51:58.353Z",
        "updated_at": "2023-09-14T01:53:59.336Z",
        "company_id": "main_entity_pk",
        "user_id": "user_entity_pk"
      }
    ],
    "roqUser": [
      {
        "reference": "eb5aa21d-b0d0-4187-a636-d39fc4e18245",
        "email": "Sammy.Wolff@hotmail.com",
        "firstName": "Demetris",
        "lastName": "Yost",
        "active": true,
        "avatarUrl": "https://avatars.githubusercontent.com/u/13696640",
        "tenantId": null
      },
      {
        "reference": "9780dc0a-0479-4897-bf2b-f67f45a553bc",
        "email": "Casandra.Mante@hotmail.com",
        "firstName": "Austin",
        "lastName": "Harber",
        "active": true,
        "avatarUrl": "https://avatars.githubusercontent.com/u/71995297",
        "tenantId": null
      },
      {
        "reference": "9fc3358a-87f0-47ea-8f99-d399d09d3b13",
        "email": "Name2@yahoo.com",
        "firstName": "Dovie",
        "lastName": "Orn",
        "active": true,
        "avatarUrl": "https://avatars.githubusercontent.com/u/57473170",
        "tenantId": null
      },
      {
        "reference": "2d760ef7-4e66-4e37-87b3-98cf2fd27c7d",
        "email": "Jordane87@gmail.com",
        "firstName": "Chyna",
        "lastName": "Runolfsdottir",
        "active": true,
        "avatarUrl": "https://avatars.githubusercontent.com/u/89966670",
        "tenantId": null
      },
      {
        "reference": "7202dccf-a54b-46b8-9950-8fc293d0612b",
        "email": "Jude_Klein27@gmail.com",
        "firstName": "Tressie",
        "lastName": "Mitchell",
        "active": true,
        "avatarUrl": "https://cloudflare-ipfs.com/ipfs/Qmd3W5DuhgHirLHGVixi6V76LhCkZUz6pnFt5AJBiyvHye/avatar/249.jpg",
        "tenantId": null
      }
    ]
  },
  {
    "customer": [
      {
        "id": "7816554a-7acd-4979-9d34-f19be711aa01",
        "first_name": "John",
        "last_name": "Doe",
        "email": "john.doe@example.com",
        "address": "123 Main St",
        "city": "New York",
        "state": "NY",
        "zip_code": "10001",
        "created_at": "2023-09-13T17:51:48.758Z",
        "updated_at": "2023-09-13T15:15:08.911Z",
        "user_id": "user_entity_pk"
      },
      {
        "id": "7c7a3d2f-e3f2-4f3e-af36-6f4a224c81b3",
        "first_name": "Jane",
        "last_name": "Smith",
        "email": "jane.smith@example.com",
        "address": "456 Elm St",
        "city": "Los Angeles",
        "state": "CA",
        "zip_code": "90001",
        "created_at": "2023-09-13T23:49:11.017Z",
        "updated_at": "2023-09-13T14:36:42.342Z",
        "user_id": "user_entity_pk"
      },
      {
        "id": "4827f6a8-34ec-4d17-b987-37220b3fd4ef",
        "first_name": "Michael",
        "last_name": "Brown",
        "email": "michael.brown@example.com",
        "address": "789 Oak St",
        "city": "Chicago",
        "state": "IL",
        "zip_code": "60601",
        "created_at": "2023-09-14T01:17:31.346Z",
        "updated_at": "2023-09-13T05:41:03.098Z",
        "user_id": "user_entity_pk"
      },
      {
        "id": "45d7660f-5f8a-4b59-8b22-1e88c389a3be",
        "first_name": "Sarah",
        "last_name": "Johnson",
        "email": "sarah.johnson@example.com",
        "address": "321 Pine St",
        "city": "Houston",
        "state": "TX",
        "zip_code": "77001",
        "created_at": "2023-09-13T17:33:48.140Z",
        "updated_at": "2023-09-13T13:27:06.509Z",
        "user_id": "user_entity_pk"
      },
      {
        "id": "150c5881-4ecc-4c94-ad68-5412b7847328",
        "first_name": "David",
        "last_name": "Wilson",
        "email": "david.wilson@example.com",
        "address": "654 Maple St",
        "city": "Phoenix",
        "state": "AZ",
        "zip_code": "85001",
        "created_at": "2023-09-13T16:42:24.206Z",
        "updated_at": "2023-09-14T01:27:09.213Z",
        "user_id": "user_entity_pk"
      }
    ],
    "service": [
      {
        "id": "8ac0512f-2ca8-4447-b525-e148e736b5d3",
        "name": "Web Development",
        "description": "Custom website development",
        "price": 88362,
        "duration": 56827,
        "created_at": "2023-09-13T19:30:38.065Z",
        "updated_at": "2023-09-13T23:03:31.427Z",
        "company_id": "main_entity_pk"
      },
      {
        "id": "446a52b5-7cca-4149-9f03-7c5c74e40b07",
        "name": "Graphic Design",
        "description": "Creative graphic design solutions",
        "price": 42583,
        "duration": 65077,
        "created_at": "2023-09-13T04:54:30.287Z",
        "updated_at": "2023-09-13T18:26:12.657Z",
        "company_id": "main_entity_pk"
      },
      {
        "id": "592f07d8-c00b-4779-ab30-b19c28e1a4e9",
        "name": "Marketing Strategy",
        "description": "Strategic marketing planning",
        "price": 80616,
        "duration": 7415,
        "created_at": "2023-09-13T08:50:35.745Z",
        "updated_at": "2023-09-13T22:18:12.082Z",
        "company_id": "main_entity_pk"
      },
      {
        "id": "1eabea47-7698-46fa-a399-2d5fa23f1863",
        "name": "IT Consulting",
        "description": "Expert IT consulting services",
        "price": 57903,
        "duration": 83922,
        "created_at": "2023-09-13T11:00:22.915Z",
        "updated_at": "2023-09-13T10:07:20.385Z",
        "company_id": "main_entity_pk"
      },
      {
        "id": "de000d9b-88ff-4c61-81df-74cfb84e9d26",
        "name": "Data Analysis",
        "description": "In-depth data analysis",
        "price": 48010,
        "duration": 96497,
        "created_at": "2023-09-13T22:37:49.122Z",
        "updated_at": "2023-09-14T00:04:51.743Z",
        "company_id": "main_entity_pk"
      }
    ],
    "request": [
      {
        "id": "1fce2e76-5d17-4257-b003-0d61c03a1b04",
        "status": "Pending",
        "created_at": "2023-09-13T04:45:09.732Z",
        "updated_at": "2023-09-13T10:25:54.666Z",
        "company_id": "main_entity_pk",
        "customer_id": "7c7a3d2f-e3f2-4f3e-af36-6f4a224c81b3",
        "service_id": "8ac0512f-2ca8-4447-b525-e148e736b5d3"
      },
      {
        "id": "0fb13e3f-b1c5-4ec3-81d7-53802d620b48",
        "status": "In Progress",
        "created_at": "2023-09-13T19:35:52.199Z",
        "updated_at": "2023-09-14T01:45:12.261Z",
        "company_id": "main_entity_pk",
        "customer_id": "45d7660f-5f8a-4b59-8b22-1e88c389a3be",
        "service_id": "446a52b5-7cca-4149-9f03-7c5c74e40b07"
      },
      {
        "id": "8da83740-d50f-4746-8569-5b11a1399909",
        "status": "Completed",
        "created_at": "2023-09-13T17:35:29.532Z",
        "updated_at": "2023-09-13T20:08:30.286Z",
        "company_id": "main_entity_pk",
        "customer_id": "7816554a-7acd-4979-9d34-f19be711aa01",
        "service_id": "de000d9b-88ff-4c61-81df-74cfb84e9d26"
      },
      {
        "id": "b42c438b-5fff-480f-9c38-261994f71f9b",
        "status": "Cancelled",
        "created_at": "2023-09-13T17:36:51.779Z",
        "updated_at": "2023-09-13T18:06:37.164Z",
        "company_id": "main_entity_pk",
        "customer_id": "4827f6a8-34ec-4d17-b987-37220b3fd4ef",
        "service_id": "446a52b5-7cca-4149-9f03-7c5c74e40b07"
      },
      {
        "id": "d87c86de-49d5-4aaf-a127-41a4caa98089",
        "status": "On Hold",
        "created_at": "2023-09-13T11:48:15.664Z",
        "updated_at": "2023-09-13T16:20:28.994Z",
        "company_id": "main_entity_pk",
        "customer_id": "7816554a-7acd-4979-9d34-f19be711aa01",
        "service_id": "1eabea47-7698-46fa-a399-2d5fa23f1863"
      }
    ],
    "representative": [
      {
        "id": "235b526d-07d5-4479-b9e0-acefb32efc30",
        "first_name": "John",
        "last_name": "Doe",
        "email": "john.doe@example.com",
        "created_at": "2023-09-13T14:29:17.024Z",
        "updated_at": "2023-09-13T23:39:54.109Z",
        "company_id": "main_entity_pk",
        "user_id": "user_entity_pk"
      },
      {
        "id": "5ef5c653-7abf-4d66-8535-af02012eac85",
        "first_name": "Jane",
        "last_name": "Smith",
        "email": "jane.smith@example.com",
        "created_at": "2023-09-13T08:57:59.485Z",
        "updated_at": "2023-09-13T14:08:51.644Z",
        "company_id": "main_entity_pk",
        "user_id": "user_entity_pk"
      },
      {
        "id": "c409b59d-4dfd-48ca-9aac-ec1b638c74eb",
        "first_name": "Michael",
        "last_name": "Brown",
        "email": "michael.brown@example.com",
        "created_at": "2023-09-13T04:30:07.356Z",
        "updated_at": "2023-09-14T00:40:07.188Z",
        "company_id": "main_entity_pk",
        "user_id": "user_entity_pk"
      },
      {
        "id": "d41f1632-9530-4a33-815f-4c390fe79855",
        "first_name": "Sarah",
        "last_name": "Johnson",
        "email": "sarah.johnson@example.com",
        "created_at": "2023-09-13T16:00:38.396Z",
        "updated_at": "2023-09-13T09:57:59.091Z",
        "company_id": "main_entity_pk",
        "user_id": "user_entity_pk"
      },
      {
        "id": "61d40c43-e3a3-4e11-bfcb-3313afd228b3",
        "first_name": "David",
        "last_name": "Wilson",
        "email": "david.wilson@example.com",
        "created_at": "2023-09-13T20:41:00.134Z",
        "updated_at": "2023-09-13T19:49:38.298Z",
        "company_id": "main_entity_pk",
        "user_id": "user_entity_pk"
      }
    ],
    "roqUser": [
      {
        "reference": "747648dc-82d0-45f1-b66f-e1efcf272a88",
        "email": "Harry_Klocko97@hotmail.com",
        "firstName": "Evie",
        "lastName": "Douglas",
        "active": true,
        "avatarUrl": "https://cloudflare-ipfs.com/ipfs/Qmd3W5DuhgHirLHGVixi6V76LhCkZUz6pnFt5AJBiyvHye/avatar/123.jpg",
        "tenantId": null
      },
      {
        "reference": "a7c317b8-179a-4b0e-a406-c7c9eb41e836",
        "email": "Cole.Emard@gmail.com",
        "firstName": "Katelyn",
        "lastName": "Bins",
        "active": true,
        "avatarUrl": "https://cloudflare-ipfs.com/ipfs/Qmd3W5DuhgHirLHGVixi6V76LhCkZUz6pnFt5AJBiyvHye/avatar/1102.jpg",
        "tenantId": null
      },
      {
        "reference": "c0a157a2-edcd-45bb-bbb7-dbe4ebc52740",
        "email": "Imelda.Mosciski14@yahoo.com",
        "firstName": "Kailee",
        "lastName": "Beier",
        "active": true,
        "avatarUrl": "https://avatars.githubusercontent.com/u/84227668",
        "tenantId": null
      },
      {
        "reference": "6404d1f4-f8ba-49a9-b667-6432ba716679",
        "email": "Chloe1@gmail.com",
        "firstName": "Camden",
        "lastName": "Collins",
        "active": true,
        "avatarUrl": "https://cloudflare-ipfs.com/ipfs/Qmd3W5DuhgHirLHGVixi6V76LhCkZUz6pnFt5AJBiyvHye/avatar/1014.jpg",
        "tenantId": null
      },
      {
        "reference": "5ea5d0a8-559c-42e3-a87f-96cb57f796c0",
        "email": "Winfield_Lynch@gmail.com",
        "firstName": "Hipolito",
        "lastName": "Marks",
        "active": true,
        "avatarUrl": "https://avatars.githubusercontent.com/u/54417823",
        "tenantId": null
      }
    ]
  },
  {
    "customer": [
      {
        "id": "f0e86888-ddbc-466f-a30c-24cb86a2a567",
        "first_name": "David",
        "last_name": "Johnson",
        "email": "david.johnson@example.com",
        "address": "123 Main St",
        "city": "New York",
        "state": "NY",
        "zip_code": "10001",
        "created_at": "2023-09-13T21:56:17.938Z",
        "updated_at": "2023-09-13T23:31:24.906Z",
        "user_id": "user_entity_pk"
      },
      {
        "id": "9021eaa4-9925-4265-bd87-3959ceaa0832",
        "first_name": "Emily",
        "last_name": "Anderson",
        "email": "emily.anderson@example.com",
        "address": "456 Elm St",
        "city": "Los Angeles",
        "state": "CA",
        "zip_code": "90001",
        "created_at": "2023-09-13T08:30:11.069Z",
        "updated_at": "2023-09-13T10:31:06.190Z",
        "user_id": "user_entity_pk"
      },
      {
        "id": "70835851-279f-4298-bf4d-60e122ac2120",
        "first_name": "Daniel",
        "last_name": "Thomas",
        "email": "daniel.thomas@example.com",
        "address": "789 Oak St",
        "city": "Chicago",
        "state": "IL",
        "zip_code": "60601",
        "created_at": "2023-09-13T06:53:10.781Z",
        "updated_at": "2023-09-14T04:09:48.747Z",
        "user_id": "user_entity_pk"
      },
      {
        "id": "bb928e2a-3ada-4197-8ec5-8ea0713b9f5a",
        "first_name": "Olivia",
        "last_name": "Robinson",
        "email": "olivia.robinson@example.com",
        "address": "321 Maple St",
        "city": "Houston",
        "state": "TX",
        "zip_code": "77001",
        "created_at": "2023-09-13T07:42:38.706Z",
        "updated_at": "2023-09-13T20:38:15.754Z",
        "user_id": "user_entity_pk"
      },
      {
        "id": "50ea2968-bd6d-481b-b984-aa38d1525a0a",
        "first_name": "Sophia",
        "last_name": "Walker",
        "email": "sophia.walker@example.com",
        "address": "654 Pine St",
        "city": "Phoenix",
        "state": "AZ",
        "zip_code": "85001",
        "created_at": "2023-09-13T15:42:18.410Z",
        "updated_at": "2023-09-13T13:10:28.694Z",
        "user_id": "user_entity_pk"
      }
    ],
    "service": [
      {
        "id": "836577b9-6b87-4bd2-80e9-cc9394c542d3",
        "name": "Web Design",
        "description": "Customized website design and development",
        "price": 61466,
        "duration": 15814,
        "created_at": "2023-09-14T01:06:00.944Z",
        "updated_at": "2023-09-13T09:53:06.525Z",
        "company_id": "main_entity_pk"
      },
      {
        "id": "4837fd33-2c92-4cdc-8224-16e81981fd6b",
        "name": "Mobile App Development",
        "description": "Creating user-friendly mobile applications",
        "price": 32321,
        "duration": 24468,
        "created_at": "2023-09-13T18:58:12.767Z",
        "updated_at": "2023-09-14T01:06:02.063Z",
        "company_id": "main_entity_pk"
      },
      {
        "id": "969657a3-6e30-4a9d-8b89-80df3e5146a3",
        "name": "Digital Marketing",
        "description": "Promoting businesses through online channels",
        "price": 8034,
        "duration": 97596,
        "created_at": "2023-09-13T06:06:22.029Z",
        "updated_at": "2023-09-13T07:26:49.268Z",
        "company_id": "main_entity_pk"
      },
      {
        "id": "8fe48427-caf3-4300-96c1-346244b5683f",
        "name": "IT Consulting",
        "description": "Providing expert advice on IT strategies",
        "price": 47102,
        "duration": 19973,
        "created_at": "2023-09-13T05:56:26.415Z",
        "updated_at": "2023-09-14T03:38:03.632Z",
        "company_id": "main_entity_pk"
      },
      {
        "id": "4e28be61-f9d3-4d29-a8c6-3f9bf3f70c10",
        "name": "Cloud Computing",
        "description": "Leveraging cloud technology for business growth",
        "price": 2884,
        "duration": 85252,
        "created_at": "2023-09-13T20:03:39.278Z",
        "updated_at": "2023-09-13T07:01:11.547Z",
        "company_id": "main_entity_pk"
      }
    ],
    "request": [
      {
        "id": "d14d3a30-3606-4965-82a2-103f4e6900ba",
        "status": "Pending",
        "created_at": "2023-09-13T14:30:49.764Z",
        "updated_at": "2023-09-13T12:57:40.705Z",
        "company_id": "main_entity_pk",
        "customer_id": "70835851-279f-4298-bf4d-60e122ac2120",
        "service_id": "8fe48427-caf3-4300-96c1-346244b5683f"
      },
      {
        "id": "90964716-4114-425c-a951-b766cb54bb1f",
        "status": "In Progress",
        "created_at": "2023-09-13T19:28:10.951Z",
        "updated_at": "2023-09-13T19:57:35.237Z",
        "company_id": "main_entity_pk",
        "customer_id": "9021eaa4-9925-4265-bd87-3959ceaa0832",
        "service_id": "8fe48427-caf3-4300-96c1-346244b5683f"
      },
      {
        "id": "42b37c7a-ca33-4941-bb61-3f2dc5f07476",
        "status": "Completed",
        "created_at": "2023-09-13T21:14:16.467Z",
        "updated_at": "2023-09-13T06:01:40.431Z",
        "company_id": "main_entity_pk",
        "customer_id": "50ea2968-bd6d-481b-b984-aa38d1525a0a",
        "service_id": "4837fd33-2c92-4cdc-8224-16e81981fd6b"
      },
      {
        "id": "bf4d66c1-537a-4084-a339-6af91c7e1f20",
        "status": "On Hold",
        "created_at": "2023-09-13T15:52:07.690Z",
        "updated_at": "2023-09-14T04:11:29.762Z",
        "company_id": "main_entity_pk",
        "customer_id": "bb928e2a-3ada-4197-8ec5-8ea0713b9f5a",
        "service_id": "836577b9-6b87-4bd2-80e9-cc9394c542d3"
      },
      {
        "id": "26e2359e-4f09-4f7d-bebc-973d9f5eb4ba",
        "status": "Cancelled",
        "created_at": "2023-09-13T05:57:22.032Z",
        "updated_at": "2023-09-14T03:03:48.727Z",
        "company_id": "main_entity_pk",
        "customer_id": "9021eaa4-9925-4265-bd87-3959ceaa0832",
        "service_id": "8fe48427-caf3-4300-96c1-346244b5683f"
      }
    ],
    "representative": [
      {
        "id": "a7679fa3-95b4-4fc5-93ef-788695a8837c",
        "first_name": "Jennifer",
        "last_name": "Brown",
        "email": "jennifer.brown@example.com",
        "created_at": "2023-09-13T12:23:34.978Z",
        "updated_at": "2023-09-13T20:17:29.928Z",
        "company_id": "main_entity_pk",
        "user_id": "user_entity_pk"
      },
      {
        "id": "398ec129-4aa8-4b6d-8de8-6a054cc75641",
        "first_name": "Michael",
        "last_name": "Johnson",
        "email": "michael.johnson@example.com",
        "created_at": "2023-09-13T07:25:51.529Z",
        "updated_at": "2023-09-14T00:45:19.864Z",
        "company_id": "main_entity_pk",
        "user_id": "user_entity_pk"
      },
      {
        "id": "94d16653-235d-4ecb-89fe-d6878050b271",
        "first_name": "Jessica",
        "last_name": "Smith",
        "email": "jessica.smith@example.com",
        "created_at": "2023-09-13T15:24:27.655Z",
        "updated_at": "2023-09-13T13:08:32.944Z",
        "company_id": "main_entity_pk",
        "user_id": "user_entity_pk"
      },
      {
        "id": "2529ecd5-0a83-4022-a563-c1d8f9400144",
        "first_name": "Christopher",
        "last_name": "Davis",
        "email": "christopher.davis@example.com",
        "created_at": "2023-09-14T03:02:30.442Z",
        "updated_at": "2023-09-13T11:45:58.403Z",
        "company_id": "main_entity_pk",
        "user_id": "user_entity_pk"
      },
      {
        "id": "e470e743-edd2-4364-b8f1-c00a765033ba",
        "first_name": "Michelle",
        "last_name": "Anderson",
        "email": "michelle.anderson@example.com",
        "created_at": "2023-09-13T06:18:25.650Z",
        "updated_at": "2023-09-13T14:30:12.645Z",
        "company_id": "main_entity_pk",
        "user_id": "user_entity_pk"
      }
    ],
    "roqUser": [
      {
        "reference": "a57e5711-f7d5-4419-a909-2dfd6d8dea72",
        "email": "Holly_Rau@hotmail.com",
        "firstName": "Eve",
        "lastName": "Schumm",
        "active": true,
        "avatarUrl": "https://avatars.githubusercontent.com/u/50528262",
        "tenantId": null
      },
      {
        "reference": "0a5c245a-5af1-48c3-ac7a-b3563ac7f00d",
        "email": "Gustave_Ritchie95@gmail.com",
        "firstName": "Chaz",
        "lastName": "MacGyver",
        "active": true,
        "avatarUrl": "https://cloudflare-ipfs.com/ipfs/Qmd3W5DuhgHirLHGVixi6V76LhCkZUz6pnFt5AJBiyvHye/avatar/583.jpg",
        "tenantId": null
      },
      {
        "reference": "7972ab49-5b39-4cc8-8e84-7f8b3ab05ad2",
        "email": "Alan_Kris@hotmail.com",
        "firstName": "Rhianna",
        "lastName": "Schroeder",
        "active": true,
        "avatarUrl": "https://avatars.githubusercontent.com/u/24708296",
        "tenantId": null
      },
      {
        "reference": "580edc7e-091b-4957-be1b-0ccfef90654e",
        "email": "Jammie_Grady@yahoo.com",
        "firstName": "Kendra",
        "lastName": "Heathcote",
        "active": true,
        "avatarUrl": "https://avatars.githubusercontent.com/u/46615888",
        "tenantId": null
      },
      {
        "reference": "47da9483-eb30-4f04-a6a7-9f39e9f84634",
        "email": "Micheal_Padberg53@yahoo.com",
        "firstName": "Fabian",
        "lastName": "Connelly",
        "active": true,
        "avatarUrl": "https://avatars.githubusercontent.com/u/89797503",
        "tenantId": null
      }
    ]
  },
  {
    "customer": [
      {
        "id": "e7285734-809c-48dd-8850-b84f21bda849",
        "first_name": "John",
        "last_name": "Doe",
        "email": "john.doe@example.com",
        "address": "123 Main St",
        "city": "New York",
        "state": "NY",
        "zip_code": "10001",
        "created_at": "2023-09-13T08:26:55.017Z",
        "updated_at": "2023-09-13T18:33:08.761Z",
        "user_id": "user_entity_pk"
      },
      {
        "id": "e6868fd8-b2b0-4a17-bd6b-76275c7e4cb4",
        "first_name": "Jane",
        "last_name": "Smith",
        "email": "jane.smith@example.com",
        "address": "456 Elm St",
        "city": "Los Angeles",
        "state": "CA",
        "zip_code": "90001",
        "created_at": "2023-09-13T10:41:07.894Z",
        "updated_at": "2023-09-13T05:03:17.708Z",
        "user_id": "user_entity_pk"
      },
      {
        "id": "986e5ea8-5073-49ea-aadf-9883197168fb",
        "first_name": "Michael",
        "last_name": "Brown",
        "email": "michael.brown@example.com",
        "address": "789 Oak St",
        "city": "Chicago",
        "state": "IL",
        "zip_code": "60601",
        "created_at": "2023-09-14T02:16:04.144Z",
        "updated_at": "2023-09-13T04:25:32.731Z",
        "user_id": "user_entity_pk"
      },
      {
        "id": "5ecd0c3d-a18f-49ba-a032-1260fec42041",
        "first_name": "Sarah",
        "last_name": "Johnson",
        "email": "sarah.johnson@example.com",
        "address": "321 Pine St",
        "city": "Houston",
        "state": "TX",
        "zip_code": "77001",
        "created_at": "2023-09-13T04:29:25.907Z",
        "updated_at": "2023-09-13T09:33:42.086Z",
        "user_id": "user_entity_pk"
      },
      {
        "id": "922737b7-e91c-4c2c-b237-07531ed49fa7",
        "first_name": "David",
        "last_name": "Wilson",
        "email": "david.wilson@example.com",
        "address": "654 Maple St",
        "city": "Phoenix",
        "state": "AZ",
        "zip_code": "85001",
        "created_at": "2023-09-13T08:39:54.675Z",
        "updated_at": "2023-09-13T13:43:30.343Z",
        "user_id": "user_entity_pk"
      }
    ],
    "service": [
      {
        "id": "b2cc615a-29ea-4aa9-8f94-01cb5b08cd06",
        "name": "Web Design",
        "description": "Professional website design services",
        "price": 13736,
        "duration": 38853,
        "created_at": "2023-09-13T21:18:05.846Z",
        "updated_at": "2023-09-13T13:03:45.138Z",
        "company_id": "main_entity_pk"
      },
      {
        "id": "eb38c091-14b4-40ad-b34d-07c3df31aa4e",
        "name": "Mobile App Development",
        "description": "Custom mobile app development",
        "price": 40041,
        "duration": 39290,
        "created_at": "2023-09-14T03:48:52.488Z",
        "updated_at": "2023-09-13T10:20:57.900Z",
        "company_id": "main_entity_pk"
      },
      {
        "id": "7df4c3e4-a99a-41c0-bf68-7bfc7e3a062e",
        "name": "Digital Marketing",
        "description": "Effective digital marketing strategies",
        "price": 22825,
        "duration": 6190,
        "created_at": "2023-09-13T19:40:26.643Z",
        "updated_at": "2023-09-13T08:55:42.394Z",
        "company_id": "main_entity_pk"
      },
      {
        "id": "064a05d1-1e0b-4ef9-b51a-39c93bd349a9",
        "name": "IT Consulting",
        "description": "Expert IT consulting services",
        "price": 31713,
        "duration": 49860,
        "created_at": "2023-09-13T20:43:26.952Z",
        "updated_at": "2023-09-13T12:37:05.494Z",
        "company_id": "main_entity_pk"
      },
      {
        "id": "98db01e3-e0ff-407d-b504-44fa572b291b",
        "name": "Cloud Solutions",
        "description": "Scalable cloud solutions",
        "price": 42820,
        "duration": 27498,
        "created_at": "2023-09-13T22:13:57.359Z",
        "updated_at": "2023-09-14T01:15:34.147Z",
        "company_id": "main_entity_pk"
      }
    ],
    "request": [
      {
        "id": "7fdb6167-3d92-4296-9dcd-dd571b642a98",
        "status": "Pending",
        "created_at": "2023-09-13T06:29:07.408Z",
        "updated_at": "2023-09-13T21:30:33.382Z",
        "company_id": "main_entity_pk",
        "customer_id": "922737b7-e91c-4c2c-b237-07531ed49fa7",
        "service_id": "b2cc615a-29ea-4aa9-8f94-01cb5b08cd06"
      },
      {
        "id": "123675ce-428f-4f45-9146-6e5b8e7df97a",
        "status": "In Progress",
        "created_at": "2023-09-13T13:57:08.099Z",
        "updated_at": "2023-09-13T06:42:54.261Z",
        "company_id": "main_entity_pk",
        "customer_id": "e7285734-809c-48dd-8850-b84f21bda849",
        "service_id": "b2cc615a-29ea-4aa9-8f94-01cb5b08cd06"
      },
      {
        "id": "473cc8be-4875-4936-b5b0-9d4b18d4e153",
        "status": "Completed",
        "created_at": "2023-09-13T07:54:11.535Z",
        "updated_at": "2023-09-14T00:10:07.459Z",
        "company_id": "main_entity_pk",
        "customer_id": "5ecd0c3d-a18f-49ba-a032-1260fec42041",
        "service_id": "b2cc615a-29ea-4aa9-8f94-01cb5b08cd06"
      },
      {
        "id": "4d75fc58-efbb-4142-a513-0f148e09a0d2",
        "status": "On Hold",
        "created_at": "2023-09-13T22:44:53.554Z",
        "updated_at": "2023-09-13T14:12:27.924Z",
        "company_id": "main_entity_pk",
        "customer_id": "e6868fd8-b2b0-4a17-bd6b-76275c7e4cb4",
        "service_id": "064a05d1-1e0b-4ef9-b51a-39c93bd349a9"
      },
      {
        "id": "579d6845-42d0-438a-bd8d-039ae21d0902",
        "status": "Cancelled",
        "created_at": "2023-09-13T23:18:09.908Z",
        "updated_at": "2023-09-13T19:40:51.223Z",
        "company_id": "main_entity_pk",
        "customer_id": "5ecd0c3d-a18f-49ba-a032-1260fec42041",
        "service_id": "7df4c3e4-a99a-41c0-bf68-7bfc7e3a062e"
      }
    ],
    "representative": [
      {
        "id": "befaff86-2c4c-4676-99f4-1a6ab29264b9",
        "first_name": "John",
        "last_name": "Doe",
        "email": "john.doe@example.com",
        "created_at": "2023-09-13T07:17:27.204Z",
        "updated_at": "2023-09-13T15:36:08.461Z",
        "company_id": "main_entity_pk",
        "user_id": "user_entity_pk"
      },
      {
        "id": "b50ad053-da1d-49d8-be7f-e7126d13d716",
        "first_name": "Jane",
        "last_name": "Smith",
        "email": "jane.smith@example.com",
        "created_at": "2023-09-13T05:39:24.771Z",
        "updated_at": "2023-09-13T18:36:50.890Z",
        "company_id": "main_entity_pk",
        "user_id": "user_entity_pk"
      },
      {
        "id": "c906e86f-2f49-4b8e-a002-7e5b50e70eb4",
        "first_name": "Michael",
        "last_name": "Brown",
        "email": "michael.brown@example.com",
        "created_at": "2023-09-13T04:36:22.730Z",
        "updated_at": "2023-09-13T04:26:12.401Z",
        "company_id": "main_entity_pk",
        "user_id": "user_entity_pk"
      },
      {
        "id": "3beb2aa8-f8a4-484b-a262-cb9f8ca854e7",
        "first_name": "Sarah",
        "last_name": "Johnson",
        "email": "sarah.johnson@example.com",
        "created_at": "2023-09-14T04:00:49.883Z",
        "updated_at": "2023-09-13T13:36:18.415Z",
        "company_id": "main_entity_pk",
        "user_id": "user_entity_pk"
      },
      {
        "id": "37508786-219e-43ee-962a-bb796eeab4b8",
        "first_name": "David",
        "last_name": "Wilson",
        "email": "david.wilson@example.com",
        "created_at": "2023-09-14T03:08:06.806Z",
        "updated_at": "2023-09-13T15:04:53.627Z",
        "company_id": "main_entity_pk",
        "user_id": "user_entity_pk"
      }
    ],
    "roqUser": [
      {
        "reference": "18f9b8af-988a-4b37-b9a5-b314770aaddf",
        "email": "Douglas_Konopelski@yahoo.com",
        "firstName": "Ceasar",
        "lastName": "Wuckert",
        "active": true,
        "avatarUrl": "https://cloudflare-ipfs.com/ipfs/Qmd3W5DuhgHirLHGVixi6V76LhCkZUz6pnFt5AJBiyvHye/avatar/582.jpg",
        "tenantId": null
      },
      {
        "reference": "3d6af06d-be02-44d0-aead-844345567156",
        "email": "Nannie.Corkery@yahoo.com",
        "firstName": "Rory",
        "lastName": "Bayer",
        "active": true,
        "avatarUrl": "https://cloudflare-ipfs.com/ipfs/Qmd3W5DuhgHirLHGVixi6V76LhCkZUz6pnFt5AJBiyvHye/avatar/457.jpg",
        "tenantId": null
      },
      {
        "reference": "a1c51f33-618f-41d9-815d-4014863351f2",
        "email": "Coy56@hotmail.com",
        "firstName": "Nicklaus",
        "lastName": "Flatley",
        "active": true,
        "avatarUrl": "https://avatars.githubusercontent.com/u/5437030",
        "tenantId": null
      },
      {
        "reference": "dba34ebd-f89b-4432-a340-4c84b2c19a01",
        "email": "Penelope95@gmail.com",
        "firstName": "Lexi",
        "lastName": "Gerlach",
        "active": true,
        "avatarUrl": "https://avatars.githubusercontent.com/u/94645618",
        "tenantId": null
      },
      {
        "reference": "6fd2290f-989c-40b1-83c8-8222c0deff47",
        "email": "Bonnie_Romaguera10@yahoo.com",
        "firstName": "Alek",
        "lastName": "Kozey",
        "active": true,
        "avatarUrl": "https://avatars.githubusercontent.com/u/65642000",
        "tenantId": null
      }
    ]
  }
]
